[{"id":64502,"word":"CIF","html":"<h1>CIF</h1><h3><i>//</i></h3><ul><li>(Econ) Giá, phí bảo hiểm, cước vận chuyển , hay giá đầy đủ của hàng hoá.</li></ul>","description":"(Econ) Giá, phí bảo hiểm, cước vận chuyển , hay giá đầy đủ của hàng hoá.","pronounce":""},{"id":64503,"word":"CIO","html":"<h1>CIO</h1><h3><i>//</i></h3><ul><li>(Econ) Xem AMERICAN FEDERATION OF LABOUR.</li></ul>","description":"(Econ) Xem AMERICAN FEDERATION OF LABOUR.","pronounce":""},{"id":60470,"word":"CISC (Complex Instruction Set Computer)","html":"<h1>CISC (Complex Instruction Set Computer)</h1><h3><i>//</i></h3><ul><li>(Tech) CISC (Máy Điện Toán dùng Bộ Chỉ Thị Phức Tạp)</li></ul>","description":"(Tech) CISC (Máy Điện Toán dùng Bộ Chỉ Thị Phức Tạp)","pronounce":""},{"id":64504,"word":"Circular flow of income","html":"<h1>Circular flow of income</h1><h3><i>//</i></h3><ul><li>(Econ) Luồng luân chuyển thu nhập.+ Luồng tiền thu và chi giữa các hãng và hộ gia đình trong nước.<br/></li></ul>","description":"(Econ) Luồng luân chuyển thu nhập.","pronounce":""},{"id":64506,"word":"Circular flow of payments","html":"<h1>Circular flow of payments</h1><h3><i>//</i></h3><ul><li>(Econ) Dòng thanh toán luân chuyển.</li></ul>","description":"(Econ) Dòng thanh toán luân chuyển.","pronounce":""},{"id":64507,"word":"Circulating capital","html":"<h1>Circulating capital</h1><h3><i>//</i></h3><ul><li>(Econ) Vốn lưu động.+ Xem WORRKING CAPITAL.<br/></li></ul>","description":"(Econ) Vốn lưu động.","pronounce":""},{"id":72544,"word":"ci","html":"<h1>ci</h1><h3><i>//</i></h3><ul><li>(vt của Channel Islands) các đảo trên biển Măngsơ</li></ul>","description":"(vt của Channel Islands) các đảo trên biển Măngsơ","pronounce":""},{"id":72545,"word":"ci-devant","html":"<h1>ci-devant</h1><h3><i>//</i></h3>* phó từ<br/><ul><li>trước đây<ul style=\"list-style-type:circle\"><li> ci-devant chairman:<i>chủ tịch trước đây</i></li></ul></li></ul>","description":"trước đây","pronounce":""},{"id":72546,"word":"cia","html":"<h1>cia</h1><h3><i>//</i></h3><ul><li>(vt của Central Intelligence Agency) Cơ quan tình báo trung ương của Hoa kỳ</li></ul>","description":"(vt của Central Intelligence Agency) Cơ quan tình báo trung ương của Hoa kỳ","pronounce":""},{"id":72547,"word":"ciao","html":"<h1>ciao</h1><h3><i>//</i></h3><ul><li>interj</li><li>chào!</li></ul>","description":"interj","pronounce":""},{"id":72548,"word":"ciborium","html":"<h1>ciborium</h1><h3><i>//</i></h3>* danh từ<br/><ul><li>số nhiều ciboria</li><li>bình đựng nước thánh</li><li>tán che ở bàn thờ chính nhà thờ</li></ul>","description":"số nhiều ciboria","pronounce":""},{"id":7851,"word":"cicada","html":"<h1>cicada</h1><h3><i>/si'kɑ:də/</i></h3><h2>danh từ</h2><ul><li>(động vật học) con ve sầu</li></ul>","description":"danh từ: (động vật học) con ve sầu","pronounce":"si'kɑ:də"},{"id":7852,"word":"cicatrice","html":"<h1>cicatrice</h1><h3><i>/'sikətris/</i></h3><h2>danh từ,  số nhiều cicatrices</h2><ul><li>cái sẹo</li><li>(thực vật học) sẹo lá</li></ul>","description":"danh từ,  số nhiều cicatrices: cái sẹo","pronounce":"'sikətris"},{"id":7853,"word":"cicatricial","html":"<h1>cicatricial</h1><h3><i>/,sikə'triʃəl/</i></h3><h2>tính từ</h2><ul><li>(thuộc) vết sẹo</li></ul>","description":"tính từ: (thuộc) vết sẹo","pronounce":",sikə'triʃəl"},{"id":7854,"word":"cicatrix","html":"<h1>cicatrix</h1><h3><i>/'sikətris/</i></h3><h2>danh từ,  số nhiều cicatrices</h2><ul><li>cái sẹo</li><li>(thực vật học) sẹo lá</li></ul>","description":"danh từ,  số nhiều cicatrices: cái sẹo","pronounce":"'sikətris"},{"id":7855,"word":"cicatrization","html":"<h1>cicatrization</h1><h3><i>/,sikətrai'zeiʃn/</i></h3><h2>danh từ</h2><ul><li>sự đóng sẹo, sự lên da non</li></ul>","description":"danh từ: sự đóng sẹo, sự lên da non","pronounce":",sikətrai'zeiʃn"},{"id":7856,"word":"cicatrize","html":"<h1>cicatrize</h1><h3><i>/'sikətraiz/</i></h3><h2>động từ</h2><ul><li>đóng sẹo; lên da non</li></ul>","description":"động từ: đóng sẹo; lên da non","pronounce":"'sikətraiz"},{"id":7857,"word":"cicerone","html":"<h1>cicerone</h1><h3><i>/,tʃitʃə'rouni/</i></h3><h2>danh từ,  số nhiều ciceroni</h2><ul><li>người dẫn đường, người hướng dẫn (đi tham quan)</li></ul>","description":"danh từ,  số nhiều ciceroni: người dẫn đường, người hướng dẫn (đi tham quan)","pronounce":",tʃitʃə'rouni"},{"id":7858,"word":"ciceroni","html":"<h1>ciceroni</h1><h3><i>/,tʃitʃə'rouni/</i></h3><h2>danh từ,  số nhiều ciceroni</h2><ul><li>người dẫn đường, người hướng dẫn (đi tham quan)</li></ul>","description":"danh từ,  số nhiều ciceroni: người dẫn đường, người hướng dẫn (đi tham quan)","pronounce":",tʃitʃə'rouni"},{"id":72549,"word":"ciceronian","html":"<h1>ciceronian</h1><h3><i>//</i></h3>* tính từ<br/><ul><li>hùng biện</li></ul>","description":"hùng biện","pronounce":""},{"id":72550,"word":"cicisbeo","html":"<h1>cicisbeo</h1><h3><i>//</i></h3>* danh từ<br/><ul><li>người con trai theo đuổi một người đàn bà có chồng</li></ul>","description":"người con trai theo đuổi một người đàn bà có chồng","pronounce":""},{"id":72551,"word":"cid","html":"<h1>cid</h1><h3><i>//</i></h3>* (viết tắt)<br/><ul><li>Cục điều tra hình sự Anh quốc (Criminal Investigation Department)</li></ul>","description":"Cục điều tra hình sự Anh quốc (Criminal Investigation Department)","pronounce":""},{"id":7859,"word":"cider","html":"<h1>cider</h1><h3><i>/'saidə/</i></h3><h2>danh từ</h2><ul><li>rượu táo</li></ul><h2>thành ngữ</h2><ol><li>more cider and less talk<ul><li>(từ Mỹ,nghĩa Mỹ),  (thông tục) làm nhiều hơn, nói ít chứ</li></ul></li></ol>","description":"danh từ: rượu táo","pronounce":"'saidə"},{"id":72552,"word":"cif","html":"<h1>cif</h1><h3><i>//</i></h3>* (viết tắt)<br/><ul><li>chi phí & bảo hiểm & cước phí (Cost & Insurance & Freight)</li></ul>","description":"chi phí & bảo hiểm & cước phí (Cost & Insurance & Freight)","pronounce":""},{"id":72553,"word":"cig","html":"<h1>cig</h1><h3><i>//</i></h3>* danh từ<br/><ul><li>(thông tục) điếu thuốc lá</li></ul>","description":"(thông tục) điếu thuốc lá","pronounce":""},{"id":7860,"word":"cigala","html":"<h1>cigala</h1><h3><i>/si'kɑ:də/</i></h3><h2>danh từ</h2><ul><li>(động vật học) con ve sầu</li></ul>","description":"danh từ: (động vật học) con ve sầu","pronounce":"si'kɑ:də"},{"id":7861,"word":"cigar","html":"<h1>cigar</h1><h3><i>/si'gɑ:/</i></h3><h2>danh từ</h2><ul><li>điếu xì gà</li></ul>","description":"danh từ: điếu xì gà","pronounce":"si'gɑ:"},{"id":7862,"word":"cigar-case","html":"<h1>cigar-case</h1><h3><i>/si'gɑ:keis/</i></h3><h2>danh từ</h2><ul><li>hộp đựng xì gà</li></ul>","description":"danh từ: hộp đựng xì gà","pronounce":"si'gɑ:keis"},{"id":7863,"word":"cigar-holder","html":"<h1>cigar-holder</h1><h3><i>/si'gɑ:,houldə/</i></h3><h2>danh từ</h2><ul><li>bót xì gà</li></ul>","description":"danh từ: bót xì gà","pronounce":"si'gɑ:,houldə"},{"id":72554,"word":"cigar-maker","html":"<h1>cigar-maker</h1><h3><i>//</i></h3>* danh từ<br/><ul><li>người quấn xì-gà</li></ul>","description":"người quấn xì-gà","pronounce":""},{"id":7864,"word":"cigar-shaped","html":"<h1>cigar-shaped</h1><h3><i>/si'gɑ:ʃeipt/</i></h3><h2>tính từ</h2><ul><li>hình xì gà, hình trụ nhọn đầu</li></ul>","description":"tính từ: hình xì gà, hình trụ nhọn đầu","pronounce":"si'gɑ:ʃeipt"},{"id":7865,"word":"cigarette","html":"<h1>cigarette</h1><h3><i>/,sigə'ret/</i></h3><h2>danh từ</h2><ul><li>điếu thuốc lá</li></ul>","description":"danh từ: điếu thuốc lá","pronounce":",sigə'ret"},{"id":7866,"word":"cigarette-case","html":"<h1>cigarette-case</h1><h3><i>/,sigə'retkeis/</i></h3><h2>danh từ</h2><ul><li>hộp đựng thuốc lá điếu</li></ul>","description":"danh từ: hộp đựng thuốc lá điếu","pronounce":",sigə'retkeis"},{"id":7867,"word":"cigarette-end","html":"<h1>cigarette-end</h1><h3><i>/,sigə'retend/</i></h3><h2>danh từ</h2><ul><li>mẩu thuốc lá (hút còn thừa)</li></ul>","description":"danh từ: mẩu thuốc lá (hút còn thừa)","pronounce":",sigə'retend"},{"id":7868,"word":"cigarette-holder","html":"<h1>cigarette-holder</h1><h3><i>/,sigə'ret,peipə/</i></h3><h2>danh từ</h2><ul><li>bót thuốc lá</li></ul>","description":"danh từ: bót thuốc lá","pronounce":",sigə'ret,peipə"},{"id":72555,"word":"cigarette-lighter","html":"<h1>cigarette-lighter</h1><h3><i>//</i></h3>* danh từ<br/><ul><li>cái bật lửa</li></ul>","description":"cái bật lửa","pronounce":""},{"id":7869,"word":"cigarette-paper","html":"<h1>cigarette-paper</h1><h3><i>/,sigə'ret,peipə/</i></h3><h2>danh từ</h2><ul><li>giấy thuốc lá</li></ul>","description":"danh từ: giấy thuốc lá","pronounce":",sigə'ret,peipə"},{"id":72556,"word":"cigarillo","html":"<h1>cigarillo</h1><h3><i>//</i></h3>* danh từ<br/><ul><li>số nhiều cigarillos</li><li>điếu thuốc lá nhỏ hở hai đầu</li></ul>","description":"số nhiều cigarillos","pronounce":""},{"id":72557,"word":"ciggie","html":"<h1>ciggie</h1><h3><i>//</i></h3>* danh từ<br/><ul><li>(thông tục) điếu thuốc lá</li></ul>","description":"(thông tục) điếu thuốc lá","pronounce":""},{"id":7870,"word":"cilia","html":"<h1>cilia</h1><h3><i>/'siliə/</i></h3><h2>danh từ số nhiều</h2><ul><li>(giải phẫu) lông mi</li><li>(sinh vật học) mao</li></ul>","description":"danh từ số nhiều: (giải phẫu) lông mi","pronounce":"'siliə"},{"id":7871,"word":"ciliary","html":"<h1>ciliary</h1><h3><i>/'siliəri/</i></h3><h2>tính từ</h2><ul><li>(giải phẫu) có lông mi</li><li>(sinh vật học) có mao</li></ul>","description":"tính từ: (giải phẫu) có lông mi","pronounce":"'siliəri"},{"id":72558,"word":"ciliate","html":"<h1>ciliate</h1><h3><i>//</i></h3>* tính từ<br/><ul><li>(sinh học) có lông rung; có lông mịn; có lông mi</li></ul>","description":"(sinh học) có lông rung; có lông mịn; có lông mi","pronounce":""},{"id":7872,"word":"ciliated","html":"<h1>ciliated</h1><h3><i>/'silieitid/</i></h3><h2>tính từ</h2><ul><li>(sinh vật học) có mao</li></ul>","description":"tính từ: (sinh vật học) có mao","pronounce":"'silieitid"},{"id":7873,"word":"cilice","html":"<h1>cilice</h1><h3><i>/'silis/</i></h3><h2>danh từ</h2><ul><li>vải tóc</li><li>áo vải tóc</li></ul>","description":"danh từ: vải tóc","pronounce":"'silis"},{"id":72559,"word":"cilium","html":"<h1>cilium</h1><h3><i>//</i></h3>* danh từ (số nhiều là cilia)<br/><ul><li>lông rung (ở tế bào thực vật)</li><li>lông mi</li></ul>","description":"lông rung (ở tế bào thực vật)","pronounce":""},{"id":72560,"word":"cillery","html":"<h1>cillery</h1><h3><i>//</i></h3>* danh từ<br/><ul><li>cũng cileri</li><li>(kiến trúc) trang trí hình lá</li></ul>","description":"cũng cileri","pronounce":""},{"id":72561,"word":"cimex","html":"<h1>cimex</h1><h3><i>//</i></h3>* danh từ<br/><ul><li>số nhiều cimices</li><li>(động vật) con rệp</li></ul>","description":"số nhiều cimices","pronounce":""},{"id":72562,"word":"cimmerian","html":"<h1>cimmerian</h1><h3><i>//</i></h3>* tính từ<br/><ul><li>tối như bưng</li></ul>","description":"tối như bưng","pronounce":""},{"id":7874,"word":"cimmerlan","html":"<h1>cimmerlan</h1><h3><i>/si'miəriən/</i></h3><h2>tính từ</h2><ul><li>tối như bưng</li></ul>","description":"tính từ: tối như bưng","pronounce":"si'miəriən"},{"id":7875,"word":"cinabar","html":"<h1>cinabar</h1><h3><i>/'sinəbɑ:/</i></h3><h2>danh từ</h2><ul><li>(hoá học) thần sa</li><li>màu son</li></ul>","description":"danh từ: (hoá học) thần sa","pronounce":"'sinəbɑ:"},{"id":7876,"word":"cinch","html":"<h1>cinch</h1><h3><i>/sintʃ/</i></h3><h2>danh từ</h2><ul><li>(từ Mỹ,nghĩa Mỹ) nịt, đai da, đai ngựa</li><li>(thông tục) sự nắm chặt, sự nịt chặt, sự ghì chặt<ul style=\"list-style-type:circle\"><li>to have a cinch on a thing:<i> nắm chặt cái gì</i></li></ul></li><li>(từ lóng) điều chắc chắn, điều xác thực; người chắc thắng, đội chắc thắng<ul style=\"list-style-type:circle\"><li>that's a cinch:<i> đó là một điều chắc chắn</i></li></ul></li></ul><h2>ngoại động từ</h2><ul><li>(từ Mỹ,nghĩa Mỹ) nịt, thắng đai (cho ngựa); cột lại, buộc chắc</li><li>(từ lóng) bảo đảm, chắc chắn</li></ul>","description":"danh từ: (từ Mỹ,nghĩa Mỹ) nịt, đai da, đai ngựa","pronounce":"sintʃ"},{"id":7877,"word":"cinchona","html":"<h1>cinchona</h1><h3><i>/siɳ'kounə/</i></h3><h2>danh từ</h2><ul><li>(thực vật học) cây canh-ki-na</li><li>vỏ canh-ki-na</li></ul>","description":"danh từ: (thực vật học) cây canh-ki-na","pronounce":"siɳ'kounə"},{"id":72563,"word":"cinchonic","html":"<h1>cinchonic</h1><h3><i>//</i></h3><ul><li>xem cinchona</li></ul>","description":"xem cinchona","pronounce":""},{"id":7878,"word":"cincture","html":"<h1>cincture</h1><h3><i>/'siɳktʃə/</i></h3><h2>danh từ</h2><ul><li>dây lưng, thắt lưng, đai lưng</li><li>thành luỹ, thành quách (xây quanh) thành phố)</li><li>(kiến trúc) đường viền (quanh cột)</li></ul><h2>ngoại động từ</h2><ul><li>thắt dây lưng, thắt đai lưng (cho ai)</li><li>bao vây, vây quanh (một thành phố)</li></ul>","description":"danh từ: dây lưng, thắt lưng, đai lưng","pronounce":"'siɳktʃə"},{"id":7879,"word":"cinder","html":"<h1>cinder</h1><h3><i>/'sində/</i></h3><h2>danh từ</h2><ul><li>thanh cháy dở</li><li>xỉ, than xỉ</li><li>cứt sắt</li><li>bọt đá (núi lửa)</li><li>(số nhiều) tro</li></ul><h2>thành ngữ</h2><ol><li>burnt to a cinder<ul><li>bị cháy sém, cháy đắng (thức ăn)</li></ul></li></ol><h2>ngoại động từ</h2><ul><li>rải than xỉ</li></ul>","description":"danh từ: thanh cháy dở","pronounce":"'sində"},{"id":7880,"word":"cinder track","html":"<h1>cinder track</h1><h3><i>/'sindəpɑ:θ/</i></h3><h2>danh từ</h2><ul><li>(thể dục,thể thao) đường chạy rải than xỉ</li></ul>","description":"danh từ: (thể dục,thể thao) đường chạy rải than xỉ","pronounce":"'sindəpɑ:θ"},{"id":7881,"word":"cinder-box","html":"<h1>cinder-box</h1><h3><i>/'sindəbɔks/</i></h3><h2>danh từ</h2><ul><li>(kỹ thuật) hộp tro</li></ul>","description":"danh từ: (kỹ thuật) hộp tro","pronounce":"'sindəbɔks"},{"id":72564,"word":"cinder-guard","html":"<h1>cinder-guard</h1><h3><i>//</i></h3>* danh từ<br/><ul><li>tấm chăn tro lửa</li></ul>","description":"tấm chăn tro lửa","pronounce":""},{"id":7882,"word":"cinder-path","html":"<h1>cinder-path</h1><h3><i>/'sindəpɑ:θ/</i></h3><h2>danh từ</h2><ul><li>(thể dục,thể thao) đường chạy rải than xỉ</li></ul>","description":"danh từ: (thể dục,thể thao) đường chạy rải than xỉ","pronounce":"'sindəpɑ:θ"},{"id":7883,"word":"cinder-sifter","html":"<h1>cinder-sifter</h1><h3><i>/'sində,siftə/</i></h3><h2>danh từ</h2><ul><li>cái sàng than xỉ</li></ul>","description":"danh từ: cái sàng than xỉ","pronounce":"'sində,siftə"},{"id":72565,"word":"cinderella","html":"<h1>cinderella</h1><h3><i>//</i></h3>* danh từ<br/><ul><li>tài năng chưa được biết đến</li></ul>","description":"tài năng chưa được biết đến","pronounce":""},{"id":7884,"word":"cindery","html":"<h1>cindery</h1><h3><i>/'sindəri/</i></h3><h2>tính từ</h2><ul><li>đầy xỉ, nhiều than xỉ</li><li>đầy tro, nhiều tro</li></ul>","description":"tính từ: đầy xỉ, nhiều than xỉ","pronounce":"'sindəri"},{"id":72566,"word":"cine","html":"<h1>cine</h1><h3><i>//</i></h3><ul><li>điện ảnh</li></ul>","description":"điện ảnh","pronounce":""},{"id":7885,"word":"cine-camera","html":"<h1>cine-camera</h1><h3><i>/'sini'kæmərə/</i></h3><h2>danh từ</h2><ul><li>máy quay phim</li></ul>","description":"danh từ: máy quay phim","pronounce":"'sini'kæmərə"},{"id":7886,"word":"cine-film","html":"<h1>cine-film</h1><h3><i>/'sinifilm/</i></h3><h2>danh từ</h2><ul><li>phim xi nê, phim chiếu bóng</li></ul>","description":"danh từ: phim xi nê, phim chiếu bóng","pronounce":"'sinifilm"},{"id":72567,"word":"cine-projector","html":"<h1>cine-projector</h1><h3><i>//</i></h3>* danh từ<br/><ul><li>máy chiếu phim</li></ul>","description":"máy chiếu phim","pronounce":""},{"id":7887,"word":"cineast","html":"<h1>cineast</h1><h3><i>/,siniæst/</i></h3><h2>danh từ</h2><ul><li>người ham chuộng nghệ thuật điện ảnh</li><li>người làm phim chiếu bóng</li></ul>","description":"danh từ: người ham chuộng nghệ thuật điện ảnh","pronounce":",siniæst"},{"id":72568,"word":"cineaste","html":"<h1>cineaste</h1><h3><i>//</i></h3>* danh từ<br/><ul><li>như cineast* danh từ<br/></li><li>như cineast</li></ul>","description":"như cineast","pronounce":""},{"id":72569,"word":"cinecamera","html":"<h1>cinecamera</h1><h3><i>//</i></h3>* danh từ<br/><ul><li>máy quay phim</li></ul>","description":"máy quay phim","pronounce":""},{"id":7888,"word":"cinema","html":"<h1>cinema</h1><h3><i>/'sinimə/</i></h3><h2>danh từ</h2><ul><li>rạp xi nê, rạp chiếu bóng</li><li>the cinema điện ảnh, xi nê, phim chiếu bóng</li><li>nghệ thuật điện ảnh; kỹ thuật điện ảnh</li></ul>","description":"danh từ: rạp xi nê, rạp chiếu bóng","pronounce":"'sinimə"},{"id":72570,"word":"cinema-circuit","html":"<h1>cinema-circuit</h1><h3><i>//</i></h3>* danh từ<br/><ul><li>các rạp chiếu bóng cùng thuộc một chủ</li></ul>","description":"các rạp chiếu bóng cùng thuộc một chủ","pronounce":""},{"id":7889,"word":"cinema-goer","html":"<h1>cinema-goer</h1><h3><i>/'sinimə,gouə/</i></h3><h2>danh từ</h2><ul><li>người xem chiếu bóng</li></ul>","description":"danh từ: người xem chiếu bóng","pronounce":"'sinimə,gouə"},{"id":7890,"word":"cinemactor","html":"<h1>cinemactor</h1><h3><i>/'sinim,æktə/</i></h3><h2>danh từ</h2><ul><li>(từ Mỹ,nghĩa Mỹ) tài tử xi nê</li></ul>","description":"danh từ: (từ Mỹ,nghĩa Mỹ) tài tử xi nê","pronounce":"'sinim,æktə"},{"id":7891,"word":"cinemactress","html":"<h1>cinemactress</h1><h3><i>/'sinim,æktris/</i></h3><h2>danh từ</h2><ul><li>(từ Mỹ,nghĩa Mỹ) nữ tài tử xi nê</li></ul>","description":"danh từ: (từ Mỹ,nghĩa Mỹ) nữ tài tử xi nê","pronounce":"'sinim,æktris"},{"id":7892,"word":"cinemaddict","html":"<h1>cinemaddict</h1><h3><i>/'sinim,ædikt/</i></h3><h2>danh từ</h2><ul><li>(từ Mỹ,nghĩa Mỹ),  (từ lóng) người nghiện xi nê, người mê xem chiếu bóng</li></ul>","description":"danh từ: (từ Mỹ,nghĩa Mỹ),  (từ lóng) người nghiện xi nê, người mê xem chiếu bóng","pronounce":"'sinim,ædikt"},{"id":72571,"word":"cinemadrama","html":"<h1>cinemadrama</h1><h3><i>//</i></h3>* danh từ<br/><ul><li>kịch chiếu phim</li></ul>","description":"kịch chiếu phim","pronounce":""},{"id":72572,"word":"cinemagoer","html":"<h1>cinemagoer</h1><h3><i>//</i></h3>* danh từ<br/><ul><li>người xem chiếu bóng</li></ul>","description":"người xem chiếu bóng","pronounce":""},{"id":7893,"word":"cinemascope","html":"<h1>cinemascope</h1><h3><i>/'siniməskoup/</i></h3><h2>danh từ</h2><ul><li>màn ảnh rộng</li></ul>","description":"danh từ: màn ảnh rộng","pronounce":"'siniməskoup"},{"id":72573,"word":"cinematheque","html":"<h1>cinematheque</h1><h3><i>//</i></h3>* danh từ<br/><ul><li>rạp chiếu bóng chuyên chiếu phim cổ điển và tiền phong</li></ul>","description":"rạp chiếu bóng chuyên chiếu phim cổ điển và tiền phong","pronounce":""},{"id":72574,"word":"cinematic","html":"<h1>cinematic</h1><h3><i>//</i></h3>* tính từ<br/><ul><li>thuộc về điện ảnh</li></ul>","description":"thuộc về điện ảnh","pronounce":""},{"id":72575,"word":"cinematically","html":"<h1>cinematically</h1><h3><i>//</i></h3><ul><li>xem cinema</li></ul>","description":"xem cinema","pronounce":""},{"id":7894,"word":"cinematics","html":"<h1>cinematics</h1><h3><i>/,sini'mætiks/</i></h3><h2>danh từ,  số nhiều dùng như số ít</h2><ul><li>nghệ thuật làm phim chiếu bóng</li><li>quá trình làm phim chiếu bóng</li></ul>","description":"danh từ,  số nhiều dùng như số ít: nghệ thuật làm phim chiếu bóng","pronounce":",sini'mætiks"},{"id":7895,"word":"cinematograph","html":"<h1>cinematograph</h1><h3><i>/,sini'mætəgrɑ:f/</i></h3><h2>danh từ</h2><ul><li>máy chiếu phim</li></ul><h2>ngoại động từ</h2><ul><li>quay phim</li></ul>","description":"danh từ: máy chiếu phim","pronounce":",sini'mætəgrɑ:f"},{"id":72576,"word":"cinematographer","html":"<h1>cinematographer</h1><h3><i>//</i></h3>* danh từ<br/><ul><li>người chuyên về điện ảnh, Nhà điện ảnh</li></ul>","description":"người chuyên về điện ảnh, Nhà điện ảnh","pronounce":""},{"id":7896,"word":"cinematographic","html":"<h1>cinematographic</h1><h3><i>/'sini,mætə'græfik/</i></h3><h2>tính từ</h2><ul><li>(thuộc) thuật quay phim</li></ul>","description":"tính từ: (thuộc) thuật quay phim","pronounce":"'sini,mætə'græfik"},{"id":72577,"word":"cinematographically","html":"<h1>cinematographically</h1><h3><i>//</i></h3><ul><li>xem cinematography</li></ul>","description":"xem cinematography","pronounce":""},{"id":7897,"word":"cinematography","html":"<h1>cinematography</h1><h3><i>/,,sinimə'tɔgrəfi/</i></h3><h2>danh từ</h2><ul><li>thuật quay phim</li></ul>","description":"danh từ: thuật quay phim","pronounce":",,sinimə'tɔgrəfi"},{"id":72578,"word":"cinerama","html":"<h1>cinerama</h1><h3><i>//</i></h3>* danh từ<br/><ul><li>màn ảnh cực rộng</li></ul>","description":"màn ảnh cực rộng","pronounce":""},{"id":7898,"word":"cineraria","html":"<h1>cineraria</h1><h3><i>/,sinə'reəriəm/</i></h3><h2>danh từ,  số nhiều cineraria</h2><ul><li>nơi để lư đựng tro hoả táng</li></ul>","description":"danh từ,  số nhiều cineraria: nơi để lư đựng tro hoả táng","pronounce":",sinə'reəriəm"},{"id":7899,"word":"cinerarium","html":"<h1>cinerarium</h1><h3><i>/,sinə'reəriəm/</i></h3><h2>danh từ,  số nhiều cineraria</h2><ul><li>nơi để lư đựng tro hoả táng</li></ul>","description":"danh từ,  số nhiều cineraria: nơi để lư đựng tro hoả táng","pronounce":",sinə'reəriəm"},{"id":7900,"word":"cinerary","html":"<h1>cinerary</h1><h3><i>/'sinərəri/</i></h3><h2>tính từ</h2><ul><li>đựng tro tàn<ul style=\"list-style-type:circle\"><li>cinerary urn:<i> lư đựng tro hoả táng</i></li></ul></li></ul>","description":"tính từ: đựng tro tàn","pronounce":"'sinərəri"},{"id":7901,"word":"cinereous","html":"<h1>cinereous</h1><h3><i>/si'niəriəs/</i></h3><h2>tính từ</h2><ul><li>(có) màu xám tro</li></ul>","description":"tính từ: (có) màu xám tro","pronounce":"si'niəriəs"},{"id":72579,"word":"cinerescent","html":"<h1>cinerescent</h1><h3><i>//</i></h3>* tính từ<br/><ul><li>có màu tro; thành màu tro</li></ul>","description":"có màu tro; thành màu tro","pronounce":""},{"id":72580,"word":"cineritious","html":"<h1>cineritious</h1><h3><i>//</i></h3>* tính từ<br/><ul><li>giống như tro</li></ul>","description":"giống như tro","pronounce":""},{"id":7902,"word":"cingalese","html":"<h1>cingalese</h1><h3><i>/,siɳgə'li:z/</i></h3><h2>tính từ</h2><ul><li>(thuộc) Xơ-ri-lan-ca</li></ul><h2>danh từ</h2><ul><li>người Xơ-ri-lan-ca</li><li>tiếng Xơ-ri-lan-ca</li></ul>","description":"tính từ: (thuộc) Xơ-ri-lan-ca","pronounce":",siɳgə'li:z"},{"id":72581,"word":"cingulum","html":"<h1>cingulum</h1><h3><i>//</i></h3>* danh từ<br/><ul><li>số nhiều cingula</li><li>đai, vành</li></ul>","description":"số nhiều cingula","pronounce":""},{"id":72582,"word":"cinnabar","html":"<h1>cinnabar</h1><h3><i>//</i></h3>* danh từ<br/><ul><li>thủy ngân sulfua (Hgs)</li><li>màu son</li><li>một loài bướm đêm có cánh đốm đỏ</li></ul>","description":"thủy ngân sulfua (Hgs)","pronounce":""},{"id":72583,"word":"cinnamic","html":"<h1>cinnamic</h1><h3><i>//</i></h3><ul><li>xem cinnamon</li></ul>","description":"xem cinnamon","pronounce":""},{"id":7903,"word":"cinnamon","html":"<h1>cinnamon</h1><h3><i>/'sinəmən/</i></h3><h2>danh từ</h2><ul><li>(thực vật học) cây quế</li><li>màu nâu vàng</li></ul>","description":"danh từ: (thực vật học) cây quế","pronounce":"'sinəmən"},{"id":104154,"word":"cinq(ue)","html":"<h1>cinq(ue)</h1><h3><i>//</i></h3><ul><li>(lý thuyết trò chơi) quân bài năm</li></ul>","description":"(lý thuyết trò chơi) quân bài năm","pronounce":""},{"id":7904,"word":"cinqfoil","html":"<h1>cinqfoil</h1><h3><i>/'siɳkfɔil/</i></h3><h2>danh từ</h2><ul><li>(thực vật học) cây ỷ lăng</li><li>(kiến trúc) kiểu trang trí ỷ lăng</li></ul>","description":"danh từ: (thực vật học) cây ỷ lăng","pronounce":"'siɳkfɔil"},{"id":72584,"word":"cinquecento","html":"<h1>cinquecento</h1><h3><i>//</i></h3>* danh từ<br/><ul><li>thế kỷ XVI ở ý (nổi tiếng về (văn học) (nghệ thuật))</li></ul>","description":"thế kỷ XVI ở ý (nổi tiếng về (văn học) (nghệ thuật))","pronounce":""},{"id":7905,"word":"cinquefoil","html":"<h1>cinquefoil</h1><h3><i>/'siɳkfɔil/</i></h3><h2>danh từ</h2><ul><li>(thực vật học) cây ỷ lăng</li><li>(kiến trúc) kiểu trang trí ỷ lăng</li></ul>","description":"danh từ: (thực vật học) cây ỷ lăng","pronounce":"'siɳkfɔil"},{"id":72585,"word":"cion","html":"<h1>cion</h1><h3><i>//</i></h3>* danh từ<br/><ul><li>cũng scion</li><li>(thực vật) cành ghép; chồi ghép</li></ul>","description":"cũng scion","pronounce":""},{"id":7906,"word":"cipher","html":"<h1>cipher</h1><h3><i>/'saifə/</i></h3><h2>danh từ</h2><ul><li>số không, số zêrô</li><li>người vô giá trị, người tầm thường; vật vô giá trị, vật tầm thường</li><li>chữ số A-rập</li><li>mật mã</li><li>chữ viết lồng nhau</li></ul><h2>thành ngữ</h2><ol><li>to stand for cipher<ul><li>hoàn toàn là một con số không, hoàn toàn vô giá trị</li></ul></li></ol><h2>ngoại động từ</h2><ul><li>tính thành số</li><li>viết thành mật mã</li></ul><h2>nội động từ</h2><ul><li>tính toán</li></ul>","description":"danh từ: số không, số zêrô","pronounce":"'saifə"},{"id":60449,"word":"cipher","html":"<h1>cipher</h1><h3><i>//</i></h3><ul><li>(Tech) mật mã; ký hiệu số</li></ul>","description":"(Tech) mật mã; ký hiệu số","pronounce":""},{"id":104155,"word":"cipher","html":"<h1>cipher</h1><h3><i>//</i></h3><ul><li>số không; ký hiệu chữ số, mà // lập mã, tính bằng chữ số</li></ul>","description":"số không; ký hiệu chữ số, mà // lập mã, tính bằng chữ số","pronounce":""},{"id":72586,"word":"ciphertext","html":"<h1>ciphertext</h1><h3><i>//</i></h3>* danh từ<br/><ul><li>văn bản viết thành mật mã</li></ul>","description":"văn bản viết thành mật mã","pronounce":""},{"id":7907,"word":"circa","html":"<h1>circa</h1><h3><i>/'sə:kə/</i></h3><h2>giới từ,  (thường) (viết tắt) c.</h2><ul><li>vào khoảng<ul style=\"list-style-type:circle\"><li>circa 1902:<i> vào khoảng năm 1902</i></li></ul></li></ul>","description":"giới từ,  (thường) (viết tắt) c.: vào khoảng","pronounce":"'sə:kə"},{"id":72587,"word":"circadian","html":"<h1>circadian</h1><h3><i>//</i></h3>* tính từ<br/><ul><li>(sinh lý học) xuất hiện khoảng một lần một ngày</li></ul>","description":"(sinh lý học) xuất hiện khoảng một lần một ngày","pronounce":""},{"id":72588,"word":"circassian","html":"<h1>circassian</h1><h3><i>//</i></h3>* danh từ<br/><ul><li>người Xiêc-cát-xi (ở Cáp-ca)</li><li>tiếng Xiếc-cát-xi</li></ul>","description":"người Xiêc-cát-xi (ở Cáp-ca)","pronounce":""},{"id":7908,"word":"circe","html":"<h1>circe</h1><h3><i>/'sə:si/</i></h3><h2>danh từ</h2><ul><li>nữ phù thuỷ (trong tác phẩm Ô-đi-xê của Hô-me)</li></ul>","description":"danh từ: nữ phù thuỷ (trong tác phẩm Ô-đi-xê của Hô-me)","pronounce":"'sə:si"},{"id":7909,"word":"circinate","html":"<h1>circinate</h1><h3><i>/'sə:sineit/</i></h3><h2>tính từ</h2><ul><li>(thực vật học) hình thoa (lá dương xỉ)</li></ul>","description":"tính từ: (thực vật học) hình thoa (lá dương xỉ)","pronounce":"'sə:sineit"},{"id":72589,"word":"circinately","html":"<h1>circinately</h1><h3><i>//</i></h3><ul><li>xem circinate</li></ul>","description":"xem circinate","pronounce":""},{"id":7910,"word":"circle","html":"<h1>circle</h1><h3><i>/'sə:kl/</i></h3><h2>danh từ</h2><ul><li>đường tròn, hình tròn<ul style=\"list-style-type:circle\"><li>polar circle:<i> vòng cực</i></li><li>vicious circle:<i> vòng luẩn quẩn</i></li></ul></li><li>sự tuần hoàn<ul style=\"list-style-type:circle\"><li>the circle of the seasons:<i> sự tuần hoàn của các mùa</i></li></ul></li><li>nhóm, giới<ul style=\"list-style-type:circle\"><li>well informed circle:<i> giới thạo tin</i></li></ul></li><li>sự chạy quanh (ngựa)</li><li>quỹ đạo (hành tinh)</li><li>phạm vi<ul style=\"list-style-type:circle\"><li>the circle of someone's activities:<i> phạm vi hoạt động của ai</i></li></ul></li><li>hàng ghế sắp tròn (trong rạp hát)</li></ul><h2>thành ngữ</h2><ol><li>to have circles round the eyes<ul><li>mắt thâm quầng</li></ul></li><li>to run round in circles<ul><li>(thông tục) chạy nhông, chạy nhắng lên (mà không được việc gì)</li></ul></li><li>to square the circle<ul><li>(xem) square</li></ul></li></ol><h2>ngoại động từ</h2><ul><li>đi chung quanh, xoay quanh<ul style=\"list-style-type:circle\"><li>the moon circles the earth:<i> mặt trăng xoay quanh quả đất</i></li></ul></li><li>vây quanh</li><li>(thể dục,thể thao) quay lộn<ul style=\"list-style-type:circle\"><li>to circle the bar:<i> quay lộn trên xà đơn</i></li></ul></li></ul><h2>nội động từ</h2><ul><li>xoay quanh; lượn tròn, lượn quanh (máy bay)</li><li>được chuyền quanh (rượu...)</li></ul><h2>thành ngữ</h2><ol><li>news circles round<ul><li>tin truyền đi, tin lan đi</li></ul></li></ol>","description":"danh từ: đường tròn, hình tròn","pronounce":"'sə:kl"},{"id":60450,"word":"circle","html":"<h1>circle</h1><h3><i>//</i></h3><ul><li>(Tech) vòng tròn; hình tròn</li></ul>","description":"(Tech) vòng tròn; hình tròn","pronounce":""},{"id":60451,"word":"circle diagram","html":"<h1>circle diagram</h1><h3><i>//</i></h3><ul><li>(Tech) sơ đồ vòng tròn/Xmit</li></ul>","description":"(Tech) sơ đồ vòng tròn/Xmit","pronounce":""},{"id":72590,"word":"circler","html":"<h1>circler</h1><h3><i>//</i></h3><ul><li>xem circle</li></ul>","description":"xem circle","pronounce":""},{"id":7911,"word":"circlet","html":"<h1>circlet</h1><h3><i>/'sə:klit/</i></h3><h2>danh từ</h2><ul><li>vòng nhỏ, vòng khuyên, nhẫn, xuyến</li></ul>","description":"danh từ: vòng nhỏ, vòng khuyên, nhẫn, xuyến","pronounce":"'sə:klit"},{"id":7912,"word":"circs","html":"<h1>circs</h1><h3><i>/'sə:ks/</i></h3><h2>danh từ số nhiều</h2><ul><li>(thông tục) (viết tắt) của circumstances</li></ul>","description":"danh từ số nhiều: (thông tục) (viết tắt) của circumstances","pronounce":"'sə:ks"},{"id":7913,"word":"circuit","html":"<h1>circuit</h1><h3><i>/'sə:kit/</i></h3><h2>danh từ</h2><ul><li>chu vi, đường vòng quanh<ul style=\"list-style-type:circle\"><li>the circuit of a town:<i> chu vi thành phố</i></li></ul></li><li>sự đi vòng quanh<ul style=\"list-style-type:circle\"><li>to make a circuit of:<i> đi vòng quanh (cái gì)</i></li></ul></li><li>cuộc kinh lý, cuộc tuần du, cuộc tuần tra (của các quan toà để xét xử); địa phận đi kinh lý</li><li>(vật lý) mạch<ul style=\"list-style-type:circle\"><li>electric circuit:<i> mạch điện</i></li></ul></li><li>(thể dục,thể thao) vòng đua</li><li>hệ thống rạp hát, rạp chiếu bóng (cùng chung một ban quản trị)</li><li>(nghĩa bóng) sự nối tiếp của sự việc...)</li></ul><h2>ngoại động từ</h2><ul><li>đi vòng quanh</li></ul>","description":"danh từ: chu vi, đường vòng quanh","pronounce":"'sə:kit"},{"id":60459,"word":"circuit","html":"<h1>circuit</h1><h3><i>//</i></h3><ul><li>(Tech) mạch điện; bản điện</li></ul>","description":"(Tech) mạch điện; bản điện","pronounce":""},{"id":104158,"word":"circuit","html":"<h1>circuit</h1><h3><i>//</i></h3><ul><li>(máy tính) mạch, chu tuyến, sơ đồ, chu trình</li><li>add c. mạch lấy tổng, mạch cộng</li><li>“and” c. mạch “và”</li><li>analogous c. mạch tương tự</li><li>anticoincidence c. mạch rẽ</li><li>antihunt (ing) c. sơ đồ chống dao động, so đồ làm ổn định</li><li>arithmetical c. mạch số học</li><li>astable c. mạch tự dao động</li><li>averaging c. mạch lấy trung bình</li><li>basic c. mạch sơ sở</li><li>brocken c. mạch gãy</li><li>commutation c. mạch chuyển, mạch đổi</li><li>compound c.s mạch đa hợp</li><li>decoding c. sơ đồ giải mã</li><li>delay c. mạch làm trễ</li><li>differentiating c. chu tuyến lấy vi phân</li><li>diode logical c. sơ đồ lôgic điôt</li><li>discriminator c. sơ đồ máy phân biệt</li><li>display c. sơ đồ báo hiệu</li><li>divide-by-two c. sơ đồ chia đôi (1:2)</li><li>doubling c. mạch tăng đôi</li><li>drive c. sơ đồ đồng bộ hoá</li><li>dual c. sơ đồ đối ngẫu</li><li>efficient c. sơ đồ hiệu dụng</li><li>electric c. mạch điện</li><li>energizing c. mạch kích thích</li><li>equivalent c. mạch tương đương</li><li>error correction c. mạch sửa sai</li><li>error indicating c. mạch phát hiện sai, mạch chỉ độ sai</li><li>exciting c. mạch kích thích</li><li>feedback c. sơ đồ liên hệ</li><li>forward c. sơ đồ tác dụng thẳng</li><li>grid c.mạch lưới</li><li>guard c. sơ đồ bảo vệ</li><li>halving c. sơ đồ chia đôi</li><li>high-frequency c. mạch cao tần</li><li>hold c. mạch cố định, mạch chặn</li><li>impulse c. mạch xung</li><li>incomplete c. mạch không đóng</li><li>inverter c. mạch nghịch đảo</li><li>linearity c. mạch tuyến tính hoá</li><li>logical c. mạch lôgic</li><li>low-order add c. mạch cộng hàng thấp</li><li>made c. mạch đóng</li><li>marking c. mạch đánh dấu</li><li>measuring c. mạch đo</li><li>memory c. mạch nhớ</li><li>metering c. mạch đo</li><li>mixing c. mạch hỗn hợp</li><li>modulator c. mạch điều phức</li><li>monitoring c. mạch ổn định đơn (có những trạng thái ổn định và tựa ổn</li><li>định)</li><li>multiple c. mạch hội</li><li>multiple output c. mạch nhiều lối ra</li><li>multi-stage c. mạch nhiều bước</li><li>network c. lưới mạch phức tạp, mạch rẽ nhánh</li><li>“not” c. mạch “không”</li><li>open ạch mở</li><li>oscillating c. mạch dao động</li><li>output c. mạch ra</li><li>parasitic c. mạch nhiễu loạn</li><li>passive c. (điều khiển học) mạch bị động</li><li>phantom c. mạch ma</li><li>power c.mạch lực</li><li>primary c. mạch sơ cấp</li><li>printed c. sơ đồ in</li><li>protection c. sơ đồ bảo vệ, mạch bảo vệ</li><li>pulse discrimination c. mạch phân biệt xung</li><li>pulse memory c. mạch nhớ xung</li><li>reducible c.s mạch khả quy</li><li>redundant c. mạch dư, mạch kép</li><li>reset c. mạch phục hồi</li><li>rewriting c. mạch ghi lại</li><li>sampling c. sơ đồ tác dụng đứt đoạn</li><li>scaling c. mạch đếm gộp</li><li>secondary c. mạch thứ cấp</li><li>sequenti al c. sơ đồ trình tự các phép tính</li><li>shift c. sơ đồ trượt</li><li>smoothing c. mạch lọc trơn, mạch san bằng</li><li>squaring c. sơ đồ hình thành các xung vuông góc</li><li>stabilizing c. chu tuyến ổn định</li><li>stamped c. sơ đồ dập</li><li>subtraction c. mạch trừ</li><li>sweep c. khối quét, mạch quét</li><li>switching c. [sơ đồ ngắt, sơ đồ đảo] mạch</li><li>symbolic(al) c. mạch ký hiệu</li><li>symmetric(al) c. sơ đồ đối xứng</li><li>synchronizing c. mạch đồng bộ hoá</li><li>test c. mạch kiểm tra</li><li>times c. sơ đồ định thời gian</li><li>typical c. sơ đồ điển hình</li></ul>","description":"(máy tính) mạch, chu tuyến, sơ đồ, chu trình","pronounce":""},{"id":7914,"word":"circuit breaker","html":"<h1>circuit breaker</h1><h3><i>/'sə:kit'breikə/</i></h3><h2>danh từ</h2><ul><li>(điện học) cái ngắt</li></ul>","description":"danh từ: (điện học) cái ngắt","pronounce":"'sə:kit'breikə"},{"id":60452,"word":"circuit breaker","html":"<h1>circuit breaker</h1><h3><i>//</i></h3><ul><li>(Tech) cái ngắt điện, ngắt mạch</li></ul>","description":"(Tech) cái ngắt điện, ngắt mạch","pronounce":""},{"id":60453,"word":"circuit capacitance","html":"<h1>circuit capacitance</h1><h3><i>//</i></h3><ul><li>(Tech) điện dung bản điện</li></ul>","description":"(Tech) điện dung bản điện","pronounce":""},{"id":60454,"word":"circuit diagram","html":"<h1>circuit diagram</h1><h3><i>//</i></h3><ul><li>(Tech) giản đồ bản điện</li></ul>","description":"(Tech) giản đồ bản điện","pronounce":""},{"id":60455,"word":"circuit layout","html":"<h1>circuit layout</h1><h3><i>//</i></h3><ul><li>(Tech) bản vẽ bản điện</li></ul>","description":"(Tech) bản vẽ bản điện","pronounce":""},{"id":60456,"word":"circuit tester","html":"<h1>circuit tester</h1><h3><i>//</i></h3><ul><li>(Tech) bộ thử bản điện</li></ul>","description":"(Tech) bộ thử bản điện","pronounce":""},{"id":60457,"word":"circuit theory","html":"<h1>circuit theory</h1><h3><i>//</i></h3><ul><li>(Tech) lý thuyết mạch điện</li></ul>","description":"(Tech) lý thuyết mạch điện","pronounce":""},{"id":60458,"word":"circuit topology","html":"<h1>circuit topology</h1><h3><i>//</i></h3><ul><li>(Tech) hình tướng mạch điện, tôpô mạch điện</li></ul>","description":"(Tech) hình tướng mạch điện, tôpô mạch điện","pronounce":""},{"id":72591,"word":"circuit training","html":"<h1>circuit training</h1><h3><i>//</i></h3>* danh từ<br/><ul><li>(thể thao) sự tập luyện một loạt bài thể dục</li></ul>","description":"(thể thao) sự tập luyện một loạt bài thể dục","pronounce":""},{"id":7915,"word":"circuit-rider","html":"<h1>circuit-rider</h1><h3><i>/'sə:kit,raidə/</i></h3><h2>danh từ</h2><ul><li>nhà giảng đạo lưu động (trong một địa phận)</li></ul>","description":"danh từ: nhà giảng đạo lưu động (trong một địa phận)","pronounce":"'sə:kit,raidə"},{"id":104159,"word":"circuital","html":"<h1>circuital</h1><h3><i>//</i></h3><ul><li>(thuộc) mạch, chu tuyến, sơ đồ</li></ul>","description":"(thuộc) mạch, chu tuyến, sơ đồ","pronounce":""},{"id":7916,"word":"circuitous","html":"<h1>circuitous</h1><h3><i>/sə'kju:itəs/</i></h3><h2>tính từ</h2><ul><li>loanh quanh, vòng quanh<ul style=\"list-style-type:circle\"><li>a circuitous route:<i> đường vòng quanh</i></li></ul></li></ul>","description":"tính từ: loanh quanh, vòng quanh","pronounce":"sə'kju:itəs"},{"id":72592,"word":"circuitously","html":"<h1>circuitously</h1><h3><i>//</i></h3>* phó từ<br/><ul><li>loanh quanh, quanh co</li></ul>","description":"loanh quanh, quanh co","pronounce":""},{"id":7917,"word":"circuitousness","html":"<h1>circuitousness</h1><h3><i>/sə'kju:itəsnis/</i></h3><h2>danh từ</h2><ul><li>sự loanh quanh, sự vòng quanh</li></ul>","description":"danh từ: sự loanh quanh, sự vòng quanh","pronounce":"sə'kju:itəsnis"},{"id":60460,"word":"circuitry","html":"<h1>circuitry</h1><h3><i>//</i></h3><ul><li>(Tech) mạch điện; hệ thống mạch điện</li></ul>","description":"(Tech) mạch điện; hệ thống mạch điện","pronounce":""},{"id":72593,"word":"circuity","html":"<h1>circuity</h1><h3><i>//</i></h3><ul><li>xem circuitous</li></ul>","description":"xem circuitous","pronounce":""},{"id":104160,"word":"circulant","html":"<h1>circulant</h1><h3><i>//</i></h3><ul><li>(thuộc) đường tròn, vòng tròn, vòng quanh</li></ul>","description":"(thuộc) đường tròn, vòng tròn, vòng quanh","pronounce":""},{"id":7918,"word":"circular","html":"<h1>circular</h1><h3><i>/'sə:kjulə/</i></h3><h2>tính từ</h2><ul><li>tròn, vòng, vòng quanh<ul style=\"list-style-type:circle\"><li>a circular building:<i> toà nhà hình tròn</i></li><li>a circular movement:<i> chuyển động vòng</i></li><li>a circular railway:<i> đường sắt vòng quanh thành phố</i></li><li>a circular tour (trip):<i> chuyến đi vòng quanh</i></li><li>a circular tour (trip):<i> chuyến đi vòng quanh</i></li><li>a circular saw:<i> cưa tròn, cưa đĩa</i></li></ul></li></ul><h2>thành ngữ</h2><ol><li>circular letter<ul><li>thông tư, thông tin</li></ul></li></ol><h2>danh từ</h2><ul><li>thông tri, thông tư</li><li>giấy báo (gửi cho khách hàng)</li></ul>","description":"tính từ: tròn, vòng, vòng quanh","pronounce":"'sə:kjulə"},{"id":60461,"word":"circular","html":"<h1>circular</h1><h3><i>//</i></h3><ul><li>(Tech) tròn; thuộc vòng tròn</li></ul>","description":"(Tech) tròn; thuộc vòng tròn","pronounce":""},{"id":60462,"word":"circular aperture","html":"<h1>circular aperture</h1><h3><i>//</i></h3><ul><li>(Tech) lỗ tròn</li></ul>","description":"(Tech) lỗ tròn","pronounce":""},{"id":60463,"word":"circular graph","html":"<h1>circular graph</h1><h3><i>//</i></h3><ul><li>(Tech) đồ thị vòng tròn</li></ul>","description":"(Tech) đồ thị vòng tròn","pronounce":""},{"id":60464,"word":"circular list","html":"<h1>circular list</h1><h3><i>//</i></h3><ul><li>(Tech) danh sách vòng tròn</li></ul>","description":"(Tech) danh sách vòng tròn","pronounce":""},{"id":72594,"word":"circular-saw","html":"<h1>circular-saw</h1><h3><i>//</i></h3>* danh từ<br/><ul><li>cưa vòng</li></ul>","description":"cưa vòng","pronounce":""},{"id":7919,"word":"circularise","html":"<h1>circularise</h1><h3><i>/'sə:kjuləraiz/</i></h3><h2>ngoại động từ</h2><ul><li>gửi thông tri, gửi thông tư</li><li>gửi giấy báo (cho khách hàng)</li></ul>","description":"ngoại động từ: gửi thông tri, gửi thông tư","pronounce":"'sə:kjuləraiz"},{"id":7920,"word":"circularity","html":"<h1>circularity</h1><h3><i>/,sə:kju'læriti/</i></h3><h2>danh từ</h2><ul><li>hình vòng tròn; dáng tròn</li></ul>","description":"danh từ: hình vòng tròn; dáng tròn","pronounce":",sə:kju'læriti"},{"id":72595,"word":"circularization","html":"<h1>circularization</h1><h3><i>//</i></h3><ul><li>xem circularize</li></ul>","description":"xem circularize","pronounce":""},{"id":7921,"word":"circularize","html":"<h1>circularize</h1><h3><i>/'sə:kjuləraiz/</i></h3><h2>ngoại động từ</h2><ul><li>gửi thông tri, gửi thông tư</li><li>gửi giấy báo (cho khách hàng)</li></ul>","description":"ngoại động từ: gửi thông tri, gửi thông tư","pronounce":"'sə:kjuləraiz"},{"id":72596,"word":"circularizer","html":"<h1>circularizer</h1><h3><i>//</i></h3><ul><li>xem circularize</li></ul>","description":"xem circularize","pronounce":""},{"id":72597,"word":"circularly","html":"<h1>circularly</h1><h3><i>//</i></h3><ul><li>xem circular</li></ul>","description":"xem circular","pronounce":""},{"id":7922,"word":"circularness","html":"<h1>circularness</h1><h3><i>/,sə:kju'læriti/</i></h3><h2>danh từ</h2><ul><li>hình vòng tròn; dáng tròn</li></ul>","description":"danh từ: hình vòng tròn; dáng tròn","pronounce":",sə:kju'læriti"},{"id":104161,"word":"circulary","html":"<h1>circulary</h1><h3><i>//</i></h3><ul><li>tròn, có hình tròn</li></ul>","description":"tròn, có hình tròn","pronounce":""},{"id":7923,"word":"circulate","html":"<h1>circulate</h1><h3><i>/'sə:kjuleit/</i></h3><h2>ngoại động từ</h2><ul><li>lưu hành, truyền, truyền bá<ul style=\"list-style-type:circle\"><li>to circulate news:<i> truyền tin</i></li></ul></li></ul><h2>nội động từ</h2><ul><li>lưu thông, luân chuyển, tuần hoàn<ul style=\"list-style-type:circle\"><li>blood circulates in the body:<i> máu lưu thông (tuần hoàn) trong cơ thể</i></li></ul></li><li>lưu hành (tiền)</li><li>lan truyền<ul style=\"list-style-type:circle\"><li>news circulates quickly:<i> tin lan truyền nhanh chóng</i></li></ul></li></ul>","description":"ngoại động từ: lưu hành, truyền, truyền bá","pronounce":"'sə:kjuleit"},{"id":104162,"word":"circulate","html":"<h1>circulate</h1><h3><i>//</i></h3><ul><li>tuần hoàn, đi vòng quanh chu trình</li></ul>","description":"tuần hoàn, đi vòng quanh chu trình","pronounce":""},{"id":72598,"word":"circulating","html":"<h1>circulating</h1><h3><i>//</i></h3>* tính từ<br/><ul><li>tuần hoàn; lưu thông</li></ul>","description":"tuần hoàn; lưu thông","pronounce":""},{"id":7924,"word":"circulating capital","html":"<h1>circulating capital</h1><h3><i>/'sə:kjuleitiɳ'kæpitl/</i></h3><h2>danh từ</h2><ul><li>vốn luân chuyển</li></ul>","description":"danh từ: vốn luân chuyển","pronounce":"'sə:kjuleitiɳ'kæpitl"},{"id":7925,"word":"circulating decimal","html":"<h1>circulating decimal</h1><h3><i>/'sə:kjuleitiɳ'desiməl/</i></h3><h2>danh từ</h2><ul><li>số thập phân, tuần hoàn</li></ul>","description":"danh từ: số thập phân, tuần hoàn","pronounce":"'sə:kjuleitiɳ'desiməl"},{"id":7926,"word":"circulating library","html":"<h1>circulating library</h1><h3><i>/'sə:kjuleitiɳ'laibrəri/</i></h3><h2>danh từ</h2><ul><li>thư viện cho mượn (cho mượn sách về nhà)</li></ul>","description":"danh từ: thư viện cho mượn (cho mượn sách về nhà)","pronounce":"'sə:kjuleitiɳ'laibrəri"},{"id":7927,"word":"circulating medium","html":"<h1>circulating medium</h1><h3><i>/'sə:kjuleitiɳ'mi:djəm/</i></h3><h2>danh từ</h2><ul><li>phương tiện trao đổi (giấy bạc, vàng...)</li></ul>","description":"danh từ: phương tiện trao đổi (giấy bạc, vàng...)","pronounce":"'sə:kjuleitiɳ'mi:djəm"},{"id":60465,"word":"circulating memory","html":"<h1>circulating memory</h1><h3><i>//</i></h3><ul><li>(Tech) bộ nhớ xoay tròn</li></ul>","description":"(Tech) bộ nhớ xoay tròn","pronounce":""},{"id":60466,"word":"circulating storage","html":"<h1>circulating storage</h1><h3><i>//</i></h3><ul><li>(Tech) bộ trữ xoay tròn</li></ul>","description":"(Tech) bộ trữ xoay tròn","pronounce":""},{"id":7928,"word":"circulation","html":"<h1>circulation</h1><h3><i>/,sə:kju'leiʃn/</i></h3><h2>danh từ</h2><ul><li>sự lưu thông<ul style=\"list-style-type:circle\"><li>the circulation of the blood:<i> sự lưu thông của máu</i></li></ul></li><li>sự lưu hành (tiền tệ<ul style=\"list-style-type:circle\"><li>to put into circulation:<i> cho lưu hành</i></li><li>to withdraw from circulation:<i> không cho lưu hành, thu hồi</i></li></ul></li><li>tổng số phát hành (báo, tạp chí...)</li><li>tiền, đồng tiền</li><li>(toán học) lưu số</li></ul>","description":"danh từ: sự lưu thông","pronounce":",sə:kju'leiʃn"},{"id":104163,"word":"circulation","html":"<h1>circulation</h1><h3><i>//</i></h3><ul><li>(giải tích) lưu số, lưu thông; sự tuần hoàn, sự lưu truyền</li><li>goods c.(toán kinh tế) sự lưu chuyển hàng hoá</li></ul>","description":"(giải tích) lưu số, lưu thông; sự tuần hoàn, sự lưu truyền","pronounce":""},{"id":72599,"word":"circulative","html":"<h1>circulative</h1><h3><i>//</i></h3><ul><li>xem circulate</li></ul>","description":"xem circulate","pronounce":""},{"id":7929,"word":"circulator","html":"<h1>circulator</h1><h3><i>/'sə:kjuleitə/</i></h3><h2>danh từ</h2><ul><li>người truyền (tin tức, mầm bệnh...)</li></ul>","description":"danh từ: người truyền (tin tức, mầm bệnh...)","pronounce":"'sə:kjuleitə"},{"id":60467,"word":"circulator","html":"<h1>circulator</h1><h3><i>//</i></h3><ul><li>(Tech) bộ xoay tròn</li></ul>","description":"(Tech) bộ xoay tròn","pronounce":""},{"id":7930,"word":"circulatory","html":"<h1>circulatory</h1><h3><i>/'sə:kjuleitəri/</i></h3><h2>tính từ</h2><ul><li>lưu thông (máu, nhựa cây)</li></ul>","description":"tính từ: lưu thông (máu, nhựa cây)","pronounce":"'sə:kjuleitəri"},{"id":104164,"word":"circum","html":"<h1>circum</h1><h3><i>//</i></h3><ul><li>chung quanh, vòng quanh</li></ul>","description":"chung quanh, vòng quanh","pronounce":""},{"id":72600,"word":"circumambience","html":"<h1>circumambience</h1><h3><i>//</i></h3><ul><li>xem circumambient</li></ul>","description":"xem circumambient","pronounce":""},{"id":7931,"word":"circumambiency","html":"<h1>circumambiency</h1><h3><i>/,sə:kəm'æmbiənsi/</i></h3><h2>danh từ</h2><ul><li>hoàn cảnh xung quanh, ngoại cảnh</li></ul>","description":"danh từ: hoàn cảnh xung quanh, ngoại cảnh","pronounce":",sə:kəm'æmbiənsi"},{"id":7932,"word":"circumambient","html":"<h1>circumambient</h1><h3><i>/,sə:kəm'æmbiənt/</i></h3><h2>tính từ</h2><ul><li>xung quanh (không khí, môi trường...)</li></ul>","description":"tính từ: xung quanh (không khí, môi trường...)","pronounce":",sə:kəm'æmbiənt"},{"id":72601,"word":"circumambiently","html":"<h1>circumambiently</h1><h3><i>//</i></h3><ul><li>xem circumambient</li></ul>","description":"xem circumambient","pronounce":""},{"id":7933,"word":"circumambulate","html":"<h1>circumambulate</h1><h3><i>/,sə:kəm'æmbjuleit/</i></h3><h2>ngoại động từ</h2><ul><li>đi vòng quanh, đi xung quanh (vật gì)</li></ul><h2>nội động từ</h2><ul><li>đi dạo, chỗ này, chỗ nọ</li><li>(nghĩa bóng) nói loanh quanh, nói quanh co</li></ul>","description":"ngoại động từ: đi vòng quanh, đi xung quanh (vật gì)","pronounce":",sə:kəm'æmbjuleit"},{"id":72602,"word":"circumambulation","html":"<h1>circumambulation</h1><h3><i>//</i></h3><ul><li>xem circumambulate</li></ul>","description":"xem circumambulate","pronounce":""},{"id":7934,"word":"circumbiendibus","html":"<h1>circumbiendibus</h1><h3><i>/,sə:kəm'bendibəs/</i></h3><h2>danh từ</h2>-(đùa cợt) phương pháp vòng quanh<br/><ul><li>lời nói quanh co uẩn khúc</li></ul>","description":"danh từ: lời nói quanh co uẩn khúc","pronounce":",sə:kəm'bendibəs"},{"id":72603,"word":"circumbuccal","html":"<h1>circumbuccal</h1><h3><i>//</i></h3>* tính từ<br/><ul><li>quanh miệng</li></ul>","description":"quanh miệng","pronounce":""},{"id":104165,"word":"circumcentre","html":"<h1>circumcentre</h1><h3><i>//</i></h3><ul><li>tâm vòng tròn ngoại tiếp</li></ul>","description":"tâm vòng tròn ngoại tiếp","pronounce":""},{"id":7935,"word":"circumcircle","html":"<h1>circumcircle</h1><h3><i>/,sə:kəm'sə:k/</i></h3><h2>danh từ</h2><ul><li>(toán học) vòng ngoại tiếp</li></ul>","description":"danh từ: (toán học) vòng ngoại tiếp","pronounce":",sə:kəm'sə:k"},{"id":60468,"word":"circumcircle","html":"<h1>circumcircle</h1><h3><i>//</i></h3><ul><li>(Tech) chu vi, vòng ngoài</li></ul>","description":"(Tech) chu vi, vòng ngoài","pronounce":""},{"id":104166,"word":"circumcirele","html":"<h1>circumcirele</h1><h3><i>//</i></h3><ul><li>vòng tròn ngoại tiếp</li></ul>","description":"vòng tròn ngoại tiếp","pronounce":""},{"id":7936,"word":"circumcise","html":"<h1>circumcise</h1><h3><i>/'sə:kəmsaiz/</i></h3><h2>ngoại động từ</h2><ul><li>cắt bao quy đầu</li><li>tẩy rửa (cõi lòng...)</li></ul>","description":"ngoại động từ: cắt bao quy đầu","pronounce":"'sə:kəmsaiz"},{"id":72604,"word":"circumciser","html":"<h1>circumciser</h1><h3><i>//</i></h3><ul><li>xem circumcise</li></ul>","description":"xem circumcise","pronounce":""},{"id":72605,"word":"circumcision","html":"<h1>circumcision</h1><h3><i>//</i></h3>* danh từ<br/><ul><li>sự cắt bao quy đầu</li></ul>","description":"sự cắt bao quy đầu","pronounce":""},{"id":7937,"word":"circumduction","html":"<h1>circumduction</h1><h3><i>/,sə:kəm'dʌkʃn/</i></h3><h2>danh từ</h2><ul><li>sự xoay quanh trục</li></ul>","description":"danh từ: sự xoay quanh trục","pronounce":",sə:kəm'dʌkʃn"},{"id":7938,"word":"circumference","html":"<h1>circumference</h1><h3><i>/sə'kʌmfərəns/</i></h3><h2>danh từ</h2><ul><li>đường tròn</li><li>chu vi</li></ul>","description":"danh từ: đường tròn","pronounce":"sə'kʌmfərəns"},{"id":104167,"word":"circumference","html":"<h1>circumference</h1><h3><i>//</i></h3><ul><li>đường tròn, chu vi vòng tròn</li><li>c. of a sphere đường tròn lớn (của hình cầu)</li></ul>","description":"đường tròn, chu vi vòng tròn","pronounce":""},{"id":7939,"word":"circumferential","html":"<h1>circumferential</h1><h3><i>/sə,kʌmfə'renʃl/</i></h3><h2>tính từ</h2><ul><li>(thuộc) đường tròn</li><li>(thuộc) chu vi</li></ul>","description":"tính từ: (thuộc) đường tròn","pronounce":"sə,kʌmfə'renʃl"},{"id":7940,"word":"circumflex","html":"<h1>circumflex</h1><h3><i>/'sə:kəmfləks/</i></h3><h2>danh từ</h2><ul><li>dấu mũ</li></ul><h2>tính từ</h2><ul><li>(thuộc) dấu mũ</li><li>(giải phẫu) hình dấu mũ, mũ<ul style=\"list-style-type:circle\"><li>circumflex artery:<i> động mạch mũ</i></li></ul></li></ul><h2>ngoại động từ</h2><ul><li>đánh dấu mũ</li></ul>","description":"danh từ: dấu mũ","pronounce":"'sə:kəmfləks"},{"id":60469,"word":"circumflex","html":"<h1>circumflex</h1><h3><i>//</i></h3><ul><li>(Tech) dấu mũ</li></ul>","description":"(Tech) dấu mũ","pronounce":""},{"id":104168,"word":"circumflex","html":"<h1>circumflex</h1><h3><i>//</i></h3><ul><li>dấu mũ</li></ul>","description":"dấu mũ","pronounce":""},{"id":7941,"word":"circumflous","html":"<h1>circumflous</h1><h3><i>/sə'kʌmfluəs/</i></h3><h2>tính từ</h2><ul><li>(như) circumfluent</li><li>có nước bao quanh</li></ul>","description":"tính từ: (như) circumfluent","pronounce":"sə'kʌmfluəs"},{"id":7942,"word":"circumfluent","html":"<h1>circumfluent</h1><h3><i>/sə'kʌmfluənt/</i></h3><h2>tính từ</h2><ul><li>chảy quanh; bao quanh</li></ul>","description":"tính từ: chảy quanh; bao quanh","pronounce":"sə'kʌmfluənt"},{"id":7943,"word":"circumfuse","html":"<h1>circumfuse</h1><h3><i>/,sə:kəm'fju:z/</i></h3><h2>ngoại động từ</h2><ul><li>làm lan ra, đổ ra xung quanh</li><li>bao quanh; làm ngập trong (ánh sáng...)</li></ul>","description":"ngoại động từ: làm lan ra, đổ ra xung quanh","pronounce":",sə:kəm'fju:z"},{"id":7944,"word":"circumfusion","html":"<h1>circumfusion</h1><h3><i>/,sə:kəm'fju:ʤn/</i></h3><h2>danh từ</h2><ul><li>sự làm lan ra, sự đổ lan ra</li><li>sự bao quanh; sự làm ngập trong (ánh sáng...)</li></ul>","description":"danh từ: sự làm lan ra, sự đổ lan ra","pronounce":",sə:kəm'fju:ʤn"},{"id":7945,"word":"circumgyrate","html":"<h1>circumgyrate</h1><h3><i>/'sə:kəm,dʤaiə'reit/</i></h3><h2>nội động từ</h2><ul><li>xoay quanh; đi quanh</li></ul>","description":"nội động từ: xoay quanh; đi quanh","pronounce":"'sə:kəm,dʤaiə'reit"},{"id":7946,"word":"circumgyration","html":"<h1>circumgyration</h1><h3><i>/'sə:kəm,dʤaiə'reiʃn/</i></h3><h2>danh từ</h2><ul><li>sự xoay quanh; sự đi quanh</li></ul>","description":"danh từ: sự xoay quanh; sự đi quanh","pronounce":"'sə:kəm,dʤaiə'reiʃn"},{"id":7947,"word":"circumjacent","html":"<h1>circumjacent</h1><h3><i>/,sə:kəmlə'kju:ʃn/</i></h3><h2>tính từ</h2><ul><li>ở xung quanh, ở bốn phía</li></ul>","description":"tính từ: ở xung quanh, ở bốn phía","pronounce":",sə:kəmlə'kju:ʃn"},{"id":72606,"word":"circumlittoral","html":"<h1>circumlittoral</h1><h3><i>//</i></h3>* tính từ<br/><ul><li>ven vùng biển</li></ul>","description":"ven vùng biển","pronounce":""},{"id":7948,"word":"circumlocution","html":"<h1>circumlocution</h1><h3><i>/,sə:kəmlə'kju:ʃn/</i></h3><h2>danh từ</h2><ul><li>lời nói quanh co luẩn quẩn; lời nói uẩn khúc</li><li>(ngôn ngữ học) ngữ giải thích</li></ul>","description":"danh từ: lời nói quanh co luẩn quẩn; lời nói uẩn khúc","pronounce":",sə:kəmlə'kju:ʃn"},{"id":72607,"word":"circumlocutorily","html":"<h1>circumlocutorily</h1><h3><i>//</i></h3><ul><li>xem circumlocution</li></ul>","description":"xem circumlocution","pronounce":""},{"id":7949,"word":"circumlocutory","html":"<h1>circumlocutory</h1><h3><i>/,sə:kəm'lɔkjutəri/</i></h3><h2>tính từ</h2><ul><li>quanh co luẩn quẩn; uẩn khúc (nói)<ul style=\"list-style-type:circle\"><li>to talk in a circumlocutory style:<i> nói quanh co luẩn quẩn</i></li></ul></li><li>(ngôn ngữ học) có tính chất ngữ giải thích</li></ul>","description":"tính từ: quanh co luẩn quẩn; uẩn khúc (nói)","pronounce":",sə:kəm'lɔkjutəri"},{"id":72608,"word":"circumlunar","html":"<h1>circumlunar</h1><h3><i>//</i></h3>* tính từ<br/><ul><li>quay quanh mặt trăng</li></ul>","description":"quay quanh mặt trăng","pronounce":""},{"id":7950,"word":"circumnavigate","html":"<h1>circumnavigate</h1><h3><i>/,sə:kəm'nævi'geiʃn/</i></h3><h2>ngoại động từ</h2><ul><li>đi vòng quanh (trái đất...) bằng đường biển</li></ul>","description":"ngoại động từ: đi vòng quanh (trái đất...) bằng đường biển","pronounce":",sə:kəm'nævi'geiʃn"},{"id":7951,"word":"circumnavigation","html":"<h1>circumnavigation</h1><h3><i>/,sə:kəm,nævi'geiʃn/</i></h3><h2>danh từ</h2><ul><li>sự đi vòng quanh bằng đường biển</li></ul>","description":"danh từ: sự đi vòng quanh bằng đường biển","pronounce":",sə:kəm,nævi'geiʃn"},{"id":72609,"word":"circumnavigator","html":"<h1>circumnavigator</h1><h3><i>//</i></h3><ul><li>xem circumnavigate</li></ul>","description":"xem circumnavigate","pronounce":""},{"id":72610,"word":"circumneural","html":"<h1>circumneural</h1><h3><i>//</i></h3>* tính từ<br/><ul><li>quanh thần kinh</li></ul>","description":"quanh thần kinh","pronounce":""},{"id":72611,"word":"circumnuclear","html":"<h1>circumnuclear</h1><h3><i>//</i></h3>* tính từ<br/><ul><li>quanh hạt nhân</li></ul>","description":"quanh hạt nhân","pronounce":""},{"id":72612,"word":"circumnutate","html":"<h1>circumnutate</h1><h3><i>//</i></h3>* nội động từ<br/><ul><li>chuyển động vòng; chuyển động xoáy ốc</li></ul>","description":"chuyển động vòng; chuyển động xoáy ốc","pronounce":""},{"id":7952,"word":"circumnutation","html":"<h1>circumnutation</h1><h3><i>/,sə:kəmnju:'teiʃn/</i></h3><h2>danh từ</h2><ul><li>(thực vật học) sự xoay xoắn ốc</li></ul>","description":"danh từ: (thực vật học) sự xoay xoắn ốc","pronounce":",sə:kəmnju:'teiʃn"},{"id":72613,"word":"circumoral","html":"<h1>circumoral</h1><h3><i>//</i></h3>* tính từ<br/><ul><li>quanh miệng</li></ul>","description":"quanh miệng","pronounce":""},{"id":72614,"word":"circumpolar","html":"<h1>circumpolar</h1><h3><i>//</i></h3>* tính từ<br/><ul><li>quanh cực (quả đất)</li><li>thấy ở trên đường chân trời<ul style=\"list-style-type:circle\"><li> a circumpolar star:<i>một ngôi sao thấy ở đường chân trời</i></li></ul></li><li>gần Bắc cực hoặc nam cực</li></ul>","description":"quanh cực (quả đất)","pronounce":""},{"id":72615,"word":"circumscissle","html":"<h1>circumscissle</h1><h3><i>//</i></h3>* tính từ<br/><ul><li>nứt theo đường vòng</li></ul>","description":"nứt theo đường vòng","pronounce":""},{"id":72616,"word":"circumscribable","html":"<h1>circumscribable</h1><h3><i>//</i></h3><ul><li>xem circumscribe</li></ul>","description":"xem circumscribe","pronounce":""},{"id":7953,"word":"circumscribe","html":"<h1>circumscribe</h1><h3><i>/'sə:kəmskrɑib/</i></h3><h2>ngoại động từ</h2><ul><li>vẽ đường xung quanh</li><li>(toán học) vẽ hình ngoại tiếp</li><li>giới hạn, hạn chế ((nghĩa đen) & (nghĩa bóng))<ul style=\"list-style-type:circle\"><li>to circumscribe someone's interests:<i> hạn chế quyền lợi của ai</i></li></ul></li><li>ký theo vòng tròn (bán kiến nghị)</li><li>định nghĩa</li></ul>","description":"ngoại động từ: vẽ đường xung quanh","pronounce":"'sə:kəmskrɑib"},{"id":72617,"word":"circumscriber","html":"<h1>circumscriber</h1><h3><i>//</i></h3><ul><li>xem circumscribe</li></ul>","description":"xem circumscribe","pronounce":""},{"id":7954,"word":"circumscription","html":"<h1>circumscription</h1><h3><i>/,sə:kəm'skripʃn/</i></h3><h2>danh từ</h2><ul><li>(toán học) sự vẽ hình ngoại tiếp</li><li>sự định giới hạn, sự hạn chế</li><li>giới hạn</li><li>khu vực địa hạt (hành chính)</li><li>hàng chữ khắc trên đường vòng (quanh đồng tiền, con dấu...)</li><li>định nghĩa</li></ul>","description":"danh từ: (toán học) sự vẽ hình ngoại tiếp","pronounce":",sə:kəm'skripʃn"},{"id":72618,"word":"circumscriptive","html":"<h1>circumscriptive</h1><h3><i>//</i></h3><ul><li>xem circumscription</li></ul>","description":"xem circumscription","pronounce":""},{"id":72619,"word":"circumscriptively","html":"<h1>circumscriptively</h1><h3><i>//</i></h3><ul><li>xem circumscription</li></ul>","description":"xem circumscription","pronounce":""},{"id":7955,"word":"circumsision","html":"<h1>circumsision</h1><h3><i>/,sə:kəm'siʤn/</i></h3><h2>danh từ</h2><ul><li>sự cắt bao quy đầu; lễ cắt bao quy đầu</li><li>the circumsision (kinh thánh) những người Do-thái</li></ul>","description":"danh từ: sự cắt bao quy đầu; lễ cắt bao quy đầu","pronounce":",sə:kəm'siʤn"},{"id":7956,"word":"circumsolar","html":"<h1>circumsolar</h1><h3><i>/,sə:kəm'soulə/</i></h3><h2>tính từ</h2><ul><li>xoay quanh mặt trời</li><li>gần mặt trời</li></ul>","description":"tính từ: xoay quanh mặt trời","pronounce":",sə:kəm'soulə"},{"id":7957,"word":"circumspect","html":"<h1>circumspect</h1><h3><i>/'sə:kəmspekt/</i></h3><h2>tính từ</h2><ul><li>thận trọng</li></ul>","description":"tính từ: thận trọng","pronounce":"'sə:kəmspekt"},{"id":7958,"word":"circumspection","html":"<h1>circumspection</h1><h3><i>/'sə:kəmspektnis/</i></h3><h2>danh từ</h2><ul><li>sự thận trọng</li></ul>","description":"danh từ: sự thận trọng","pronounce":"'sə:kəmspektnis"},{"id":72620,"word":"circumspectly","html":"<h1>circumspectly</h1><h3><i>//</i></h3>* phó từ<br/><ul><li>dè dặt, thận trọng</li></ul>","description":"dè dặt, thận trọng","pronounce":""},{"id":7959,"word":"circumspectness","html":"<h1>circumspectness</h1><h3><i>/'sə:kəmspektnis/</i></h3><h2>danh từ</h2><ul><li>sự thận trọng</li></ul>","description":"danh từ: sự thận trọng","pronounce":"'sə:kəmspektnis"},{"id":104169,"word":"circumsphere","html":"<h1>circumsphere</h1><h3><i>//</i></h3><ul><li>mặt cầu ngoại tiếp</li></ul>","description":"mặt cầu ngoại tiếp","pronounce":""},{"id":7960,"word":"circumstance","html":"<h1>circumstance</h1><h3><i>/'sə:kəmstəns/</i></h3><h2>danh từ số nhiều</h2><ul><li>hoàn cảnh, trường hợp, tình huống<ul style=\"list-style-type:circle\"><li>under (in) the present circumstances:<i> trong hoàn cảnh hiện tại</i></li><li>under (in) no circumstances:<i> dù trong hoàn cảnh nào cũng không bao giờ</i></li><li>to live in narrow circumstances:<i> sống thiếu thốn nghèo túng</i></li><li>in easy (good, flourishing) circumstances:<i> trong hoàn cảnh sung túc phong lưu</i></li><li>in bad (straitened) circumstances:<i> trong hoàn cảnh thiếu thốn túng quẫn</i></li></ul></li><li>sự kiện, sự việc, chi tiết<ul style=\"list-style-type:circle\"><li>to tell a story without omitting a single circumstance:<i> kể câu chuyện không bỏ sót một chi tiết nào</i></li></ul></li><li>nghi thức, nghi lễ<ul style=\"list-style-type:circle\"><li>to receive someone with pomp and circumstance:<i> tiếp đón ai (với nghi thức) rất trọng thể</i></li></ul></li></ul><h2>thành ngữ</h2><ol><li>to be behind hand in one's circumstances<ul><li>túng thiếu, thiếu tiền</li></ul></li><li>circumstances alter cases<ul><li>tất cả đề chỉ do hoàn cảnh tạo ra cả; có tội lỗi chẳng qua cũng chỉ vì hoàn cảnh xui nên<ul style=\"list-style-type:circle\"><li>not a circumstance to:<i> (từ Mỹ,nghĩa Mỹ),  (từ lóng) không thể so sánh với, không ra cái gì khi đem so sánh với</i></li></ul></li></ul></li></ol>","description":"danh từ số nhiều: hoàn cảnh, trường hợp, tình huống","pronounce":"'sə:kəmstəns"},{"id":7961,"word":"circumstantial","html":"<h1>circumstantial</h1><h3><i>/,sə:kəm'stænʃl/</i></h3><h2>tính từ</h2><ul><li>tường tận, chi tiết<ul style=\"list-style-type:circle\"><li>a circumstantial repeort:<i> bản báo cáo chi tiết</i></li></ul></li><li>(pháp lý) gián tiếp; dựa vào những chi tiết phụ; do suy diễn<ul style=\"list-style-type:circle\"><li>circumstantial evidence:<i> chứng cớ gián tiếp</i></li></ul></li><li>(thuộc) hoàn cảnh, (thuộc) trường hợp, (thuộc) tình huống; do hoàn cảnh; tuỳ theo hoàn cảnh</li><li>xảy ra bất ngờ</li></ul>","description":"tính từ: tường tận, chi tiết","pronounce":",sə:kəm'stænʃl"},{"id":7962,"word":"circumstantiality","html":"<h1>circumstantiality</h1><h3><i>/'sə:kəm,stænʃi'æliti/</i></h3><h2>danh từ</h2><ul><li>sự phong phú về chi tiết</li></ul>","description":"danh từ: sự phong phú về chi tiết","pronounce":"'sə:kəm,stænʃi'æliti"},{"id":7963,"word":"circumstantially","html":"<h1>circumstantially</h1><h3><i>/,sə:kəm'stænʃəli/</i></h3><h2>phó từ</h2><ul><li>với nhiều chi tiết, tường tận</li></ul>","description":"phó từ: với nhiều chi tiết, tường tận","pronounce":",sə:kəm'stænʃəli"},{"id":7964,"word":"circumstantiate","html":"<h1>circumstantiate</h1><h3><i>/,sə:kəm'stænʃieit/</i></h3><h2>ngoại động từ</h2><ul><li>xác minh bằng những chi tiết</li><li>tả chi tiết, nói chi tiết, cho chi tiết</li></ul>","description":"ngoại động từ: xác minh bằng những chi tiết","pronounce":",sə:kəm'stænʃieit"},{"id":72621,"word":"circumstantiation","html":"<h1>circumstantiation</h1><h3><i>//</i></h3><ul><li>xem circumstantiate</li></ul>","description":"xem circumstantiate","pronounce":""},{"id":72622,"word":"circumstellar","html":"<h1>circumstellar</h1><h3><i>//</i></h3>* tính từ<br/><ul><li>ở cạnh một ngôi sao</li></ul>","description":"ở cạnh một ngôi sao","pronounce":""},{"id":7965,"word":"circumvallate","html":"<h1>circumvallate</h1><h3><i>/,sə:kəm'væleit/</i></h3><h2>ngoại động từ</h2><ul><li>(sử học) xây đắp thành luỹ xung quanh (doanh trại...)</li></ul>","description":"ngoại động từ: (sử học) xây đắp thành luỹ xung quanh (doanh trại...)","pronounce":",sə:kəm'væleit"},{"id":7966,"word":"circumvallation","html":"<h1>circumvallation</h1><h3><i>/,sə:kəmvə'leiʃn/</i></h3><h2>danh từ</h2><ul><li>(sử học) sự xây đắp thành luỹ xung quanh (doanh trại...)</li></ul>","description":"danh từ: (sử học) sự xây đắp thành luỹ xung quanh (doanh trại...)","pronounce":",sə:kəmvə'leiʃn"},{"id":72623,"word":"circumvascular","html":"<h1>circumvascular</h1><h3><i>//</i></h3>* tính từ<br/><ul><li>(sinh học) quanh mạch</li></ul>","description":"(sinh học) quanh mạch","pronounce":""},{"id":7967,"word":"circumvent","html":"<h1>circumvent</h1><h3><i>/,sə:kəm'vent/</i></h3><h2>ngoại động từ</h2><ul><li>dùng mưu để lừa; dùng mưu kế để lung lạc (ai)</li><li>phá vỡ, làm hỏng (kế hoạch của ai...)</li></ul>","description":"ngoại động từ: dùng mưu để lừa; dùng mưu kế để lung lạc (ai)","pronounce":",sə:kəm'vent"},{"id":72624,"word":"circumventer","html":"<h1>circumventer</h1><h3><i>//</i></h3><ul><li>xem circumvent</li></ul>","description":"xem circumvent","pronounce":""},{"id":7968,"word":"circumvention","html":"<h1>circumvention</h1><h3><i>/,sə:kəm'venʃn/</i></h3><h2>danh từ</h2><ul><li>sự dùng mưu để lừa; sự dùng mưu kế để lung lạc (ai)</li><li>sự phá vỡ (kế hoạch, mưu kế của ai...)</li></ul>","description":"danh từ: sự dùng mưu để lừa; sự dùng mưu kế để lung lạc (ai)","pronounce":",sə:kəm'venʃn"},{"id":72625,"word":"circumventive","html":"<h1>circumventive</h1><h3><i>//</i></h3><ul><li>xem circumvent</li></ul>","description":"xem circumvent","pronounce":""},{"id":72626,"word":"circumventor","html":"<h1>circumventor</h1><h3><i>//</i></h3><ul><li>xem circumvent</li></ul>","description":"xem circumvent","pronounce":""},{"id":7969,"word":"circumvolution","html":"<h1>circumvolution</h1><h3><i>/,sə:kəmvə'lju:ʃn/</i></h3><h2>danh từ</h2><ul><li>sự cuộn tròn, sự xoay quanh</li><li>nếp, cuộn<ul style=\"list-style-type:circle\"><li>the circumvolution s of the brain:<i> nếp cuộn của não</i></li></ul></li><li>sự đi quanh co</li></ul>","description":"danh từ: sự cuộn tròn, sự xoay quanh","pronounce":",sə:kəmvə'lju:ʃn"},{"id":7970,"word":"circus","html":"<h1>circus</h1><h3><i>/'sə:kəs/</i></h3><h2>danh từ</h2><ul><li>rạp xiếc</li><li>gánh xiếc</li><li>chỗ nhiều đường gặp nhau</li><li>tiếng huyên náo, trò chơi ồn ào</li><li>trường đấu, trường du hí (ở cổ La-mã)</li><li>(địa lý,địa chất) đai vòng</li></ul>","description":"danh từ: rạp xiếc","pronounce":"'sə:kəs"},{"id":72627,"word":"circusy","html":"<h1>circusy</h1><h3><i>//</i></h3><ul><li>xem circus</li></ul>","description":"xem circus","pronounce":""},{"id":104156,"word":"cirele","html":"<h1>cirele</h1><h3><i>//</i></h3><ul><li>vòng tròn, đường tròn, hình tròn c. at infinity vòng ở vô tận,</li></ul>","description":"vòng tròn, đường tròn, hình tròn c. at infinity vòng ở vô tận,","pronounce":""},{"id":7971,"word":"cirque","html":"<h1>cirque</h1><h3><i>/'sə:k/</i></h3><h2>danh từ</h2><ul><li>(thơ ca) trường đua, trường đấu</li><li>(địa lý,địa chất) đài vòng</li></ul>","description":"danh từ: (thơ ca) trường đua, trường đấu","pronounce":"'sə:k"},{"id":72628,"word":"cirrate","html":"<h1>cirrate</h1><h3><i>//</i></h3>* tính từ<br/><ul><li>(sinh học) có tua cuốn; có lông gai</li></ul>","description":"(sinh học) có tua cuốn; có lông gai","pronounce":""},{"id":7972,"word":"cirrhosis","html":"<h1>cirrhosis</h1><h3><i>/si'rousis/</i></h3><h2>danh từ</h2><ul><li>(y học) bệnh xơ gan</li></ul>","description":"danh từ: (y học) bệnh xơ gan","pronounce":"si'rousis"},{"id":72629,"word":"cirrhotic","html":"<h1>cirrhotic</h1><h3><i>//</i></h3><ul><li>xem cirrhosis</li></ul>","description":"xem cirrhosis","pronounce":""},{"id":7973,"word":"cirri","html":"<h1>cirri</h1><h3><i>/'sirəs/</i></h3><h2>danh từ,  số nhiều cirri</h2><ul><li>(thực vật học) tua cuốn</li><li>(động vật học) lông gai</li><li>(khí tượng) mây ti</li></ul>","description":"danh từ,  số nhiều cirri: (thực vật học) tua cuốn","pronounce":"'sirəs"},{"id":7974,"word":"cirriferous","html":"<h1>cirriferous</h1><h3><i>/si'rifərəs/</i></h3><h2>tính từ</h2><ul><li>(thực vật học) có tua cuốn</li><li>(động vật học) có lông gai</li></ul>","description":"tính từ: (thực vật học) có tua cuốn","pronounce":"si'rifərəs"},{"id":7975,"word":"cirriform","html":"<h1>cirriform</h1><h3><i>/'sirifɔ:m/</i></h3><h2>tính từ</h2><ul><li>hình tua cuốn</li><li>hình lông gai</li></ul>","description":"tính từ: hình tua cuốn","pronounce":"'sirifɔ:m"},{"id":7976,"word":"cirriped","html":"<h1>cirriped</h1><h3><i>/'siriped/</i></h3><h2>danh từ</h2><ul><li>(động vật học) loài chân tơ</li></ul>","description":"danh từ: (động vật học) loài chân tơ","pronounce":"'siriped"},{"id":7977,"word":"cirripede","html":"<h1>cirripede</h1><h3><i>/'siriped/</i></h3><h2>danh từ</h2><ul><li>(động vật học) loài chân tơ</li></ul>","description":"danh từ: (động vật học) loài chân tơ","pronounce":"'siriped"},{"id":7978,"word":"cirro-cumulus","html":"<h1>cirro-cumulus</h1><h3><i>/'sirou'kju:mjuləs/</i></h3><h2>danh từ</h2><ul><li>mây ti tích</li></ul>","description":"danh từ: mây ti tích","pronounce":"'sirou'kju:mjuləs"},{"id":7979,"word":"cirro-stratus","html":"<h1>cirro-stratus</h1><h3><i>/'sirou'strɑ:təs/</i></h3><h2>danh từ</h2><ul><li>mây ti tầng</li></ul>","description":"danh từ: mây ti tầng","pronounce":"'sirou'strɑ:təs"},{"id":7980,"word":"cirrose","html":"<h1>cirrose</h1><h3><i>/'sirous/</i></h3><h2>tính từ</h2><ul><li>có tua cuốn; hình tua cuốn</li><li>có lông gai; hình lông gai</li><li>(khí tượng) (thuộc) mây ti</li></ul>","description":"tính từ: có tua cuốn; hình tua cuốn","pronounce":"'sirous"},{"id":7981,"word":"cirrous","html":"<h1>cirrous</h1><h3><i>/'sirous/</i></h3><h2>tính từ</h2><ul><li>có tua cuốn; hình tua cuốn</li><li>có lông gai; hình lông gai</li><li>(khí tượng) (thuộc) mây ti</li></ul>","description":"tính từ: có tua cuốn; hình tua cuốn","pronounce":"'sirous"},{"id":7982,"word":"cirrus","html":"<h1>cirrus</h1><h3><i>/'sirəs/</i></h3><h2>danh từ,  số nhiều cirri</h2><ul><li>(thực vật học) tua cuốn</li><li>(động vật học) lông gai</li><li>(khí tượng) mây ti</li></ul>","description":"danh từ,  số nhiều cirri: (thực vật học) tua cuốn","pronounce":"'sirəs"},{"id":72630,"word":"cisalpine","html":"<h1>cisalpine</h1><h3><i>//</i></h3>* tính từ<br/><ul><li>ở phía nam của dãy Alps</li></ul>","description":"ở phía nam của dãy Alps","pronounce":""},{"id":72631,"word":"cisatlantic","html":"<h1>cisatlantic</h1><h3><i>//</i></h3>* tính từ<br/><ul><li>phía châu Âu của Đại-tây-dương</li></ul>","description":"phía châu Âu của Đại-tây-dương","pronounce":""},{"id":72632,"word":"cisc","html":"<h1>cisc</h1><h3><i>//</i></h3><ul><li>máy tính có tập lệnh phức hợp</li></ul>","description":"máy tính có tập lệnh phức hợp","pronounce":""},{"id":72633,"word":"cislunar","html":"<h1>cislunar</h1><h3><i>//</i></h3>* tính từ<br/><ul><li>nằm giữa quả đất và mặt trăng<ul style=\"list-style-type:circle\"><li> cislunar space:<i>không gian giữa quả đất và mặt trăng</i></li></ul></li></ul>","description":"nằm giữa quả đất và mặt trăng","pronounce":""},{"id":7983,"word":"cissoid","html":"<h1>cissoid</h1><h3><i>/'sisɔid/</i></h3><h2>danh từ</h2><ul><li>(toán học) đường xixôit</li></ul>","description":"danh từ: (toán học) đường xixôit","pronounce":"'sisɔid"},{"id":104170,"word":"cissoid","html":"<h1>cissoid</h1><h3><i>//</i></h3><ul><li>xixôit (đồ thị của y (2x-x)=x )</li></ul>","description":"xixôit (đồ thị của y (2x-x)=x )","pronounce":""},{"id":7984,"word":"cissy","html":"<h1>cissy</h1><h3><i>/'sisi/</i></h3><h2>danh từ</h2><ul><li>(từ Mỹ,nghĩa Mỹ),  (từ lóng) người ẻo lả vì yếu đuối</li></ul>","description":"danh từ: (từ Mỹ,nghĩa Mỹ),  (từ lóng) người ẻo lả vì yếu đuối","pronounce":"'sisi"},{"id":7985,"word":"cist","html":"<h1>cist</h1><h3><i>/sist/</i></h3><h2>danh từ</h2><ul><li>mộ (đá, thân cây khoét, thời tiền sử)</li><li>hòm đựng đồ thánh</li></ul>","description":"danh từ: mộ (đá, thân cây khoét, thời tiền sử)","pronounce":"sist"},{"id":72634,"word":"cistercian","html":"<h1>cistercian</h1><h3><i>//</i></h3>* danh từ<br/><ul><li>cha cố thuộc dòng Xitô (Robert Citeaux)</li></ul>","description":"cha cố thuộc dòng Xitô (Robert Citeaux)","pronounce":""},{"id":7986,"word":"cistern","html":"<h1>cistern</h1><h3><i>/'sistən/</i></h3><h2>danh từ</h2><ul><li>thùng chứa nước, bể chứa nước (ở trên nóc nhà)</li><li>bể chứa, bình chứa<ul style=\"list-style-type:circle\"><li>the cistern of a barometer:<i> bình (chứa) thuỷ ngân của phong vũ biểu</i></li></ul></li></ul>","description":"danh từ: thùng chứa nước, bể chứa nước (ở trên nóc nhà)","pronounce":"'sistən"},{"id":72635,"word":"cisterna","html":"<h1>cisterna</h1><h3><i>//</i></h3>* danh từ<br/><ul><li>số nhiều cisternae</li><li>(sinh học) túi đựng dịch<ul style=\"list-style-type:circle\"><li> cisterna chyle:<i>túi nhũ trấp</i></li></ul></li></ul>","description":"số nhiều cisternae","pronounce":""},{"id":72636,"word":"cisternal","html":"<h1>cisternal</h1><h3><i>//</i></h3><ul><li>xem cistern</li></ul>","description":"xem cistern","pronounce":""},{"id":72637,"word":"cistron","html":"<h1>cistron</h1><h3><i>//</i></h3>* danh từ<br/><ul><li>(sinh học) xitron (gen, đơn vị di truyền chức năng)</li></ul>","description":"(sinh học) xitron (gen, đơn vị di truyền chức năng)","pronounce":""},{"id":7987,"word":"cit","html":"<h1>cit</h1><h3><i>/sit/</i></h3><h2>danh từ</h2><ul><li>người dân thành thị</li><li>(từ lóng) thường dân, người thường (trái với quân đội)</li></ul><h2>thành ngữ</h2><ol><li>officers in cits<ul><li>(từ Mỹ,nghĩa Mỹ) sĩ quan mặc thường phục</li></ul></li></ol>","description":"danh từ: người dân thành thị","pronounce":"sit"},{"id":72638,"word":"citable","html":"<h1>citable</h1><h3><i>//</i></h3><ul><li>xem cite</li></ul>","description":"xem cite","pronounce":""},{"id":7988,"word":"citadel","html":"<h1>citadel</h1><h3><i>/'sitədl/</i></h3><h2>danh từ</h2><ul><li>thành luỹ, thành quách, thành trì</li><li>chỗ ẩn tránh cuối cùng, chỗ ẩn náu cuối cùng (trong lúc nguy nan), thành luỹ cuối cùng</li></ul>","description":"danh từ: thành luỹ, thành quách, thành trì","pronounce":"'sitədl"},{"id":7989,"word":"citation","html":"<h1>citation</h1><h3><i>/sai'teiʃn/</i></h3><h2>danh từ</h2><ul><li>sự dẫn, sự trích dẫn</li><li>câu trích dẫn, đoạn trích dẫn</li><li>(pháp lý) trát đòi hầu toà</li><li>(từ Mỹ,nghĩa Mỹ),  (quân sự) sự biểu dương, sự tuyên dương</li></ul>","description":"danh từ: sự dẫn, sự trích dẫn","pronounce":"sai'teiʃn"},{"id":72639,"word":"citational","html":"<h1>citational</h1><h3><i>//</i></h3><ul><li>xem citation</li></ul>","description":"xem citation","pronounce":""},{"id":72640,"word":"citatory","html":"<h1>citatory</h1><h3><i>//</i></h3><ul><li>xem citation</li></ul>","description":"xem citation","pronounce":""},{"id":7990,"word":"cite","html":"<h1>cite</h1><h3><i>/sait/</i></h3><h2>ngoại động từ</h2><ul><li>dẫn, trích dẫn<ul style=\"list-style-type:circle\"><li>to someone's words:<i> dẫn lời nói của ai</i></li></ul></li><li>(pháp lý) đòi ra toà<ul style=\"list-style-type:circle\"><li>to cite someone before a court:<i> đòi ai ra trước toà</i></li></ul></li><li>nêu gương</li><li>(từ Mỹ,nghĩa Mỹ),  (quân sự) biểu dương, tuyên dương</li></ul>","description":"ngoại động từ: dẫn, trích dẫn","pronounce":"sait"},{"id":72641,"word":"cithara","html":"<h1>cithara</h1><h3><i>//</i></h3>* danh từ<br/><ul><li>đàn xi-ta; đàn thập lục</li></ul>","description":"đàn xi-ta; đàn thập lục","pronounce":""},{"id":72642,"word":"cither(n)","html":"<h1>cither(n)</h1><h3><i>//</i></h3>* danh từ<br/><ul><li>đàn xít</li></ul>","description":"đàn xít","pronounce":""},{"id":7991,"word":"citified","html":"<h1>citified</h1><h3><i>/'sitifaid/</i></h3><h2>tính từ</h2><ul><li>có bộ tịch thành thị, có vẻ người thành thị</li></ul>","description":"tính từ: có bộ tịch thành thị, có vẻ người thành thị","pronounce":"'sitifaid"},{"id":7992,"word":"citizen","html":"<h1>citizen</h1><h3><i>/'sitizn/</i></h3><h2>danh từ</h2><ul><li>người dân thành thị</li><li>công dân, dân</li><li>(từ Mỹ,nghĩa Mỹ) người thường dân (trái với quân đội)</li></ul><h2>thành ngữ</h2><ol><li>citizen of the world<ul><li>công dân thế giới, người theo chủ nghĩa siêu quốc gia</li></ul></li></ol>","description":"danh từ: người dân thành thị","pronounce":"'sitizn"},{"id":72643,"word":"citizen's arrest","html":"<h1>citizen's arrest</h1><h3><i>//</i></h3><ul><li>sự bắt giữ do thường dân thực hiện</li></ul>","description":"sự bắt giữ do thường dân thực hiện","pronounce":""},{"id":60471,"word":"citizen's radio band","html":"<h1>citizen's radio band</h1><h3><i>//</i></h3><ul><li>(Tech) băng tần dân dụng</li></ul>","description":"(Tech) băng tần dân dụng","pronounce":""},{"id":72644,"word":"citizenly","html":"<h1>citizenly</h1><h3><i>//</i></h3><ul><li>xem citizen</li></ul>","description":"xem citizen","pronounce":""},{"id":72645,"word":"citizenry","html":"<h1>citizenry</h1><h3><i>//</i></h3>* danh từ<br/><ul><li>toàn thể công dân</li></ul>","description":"toàn thể công dân","pronounce":""},{"id":72646,"word":"citizens band","html":"<h1>citizens band</h1><h3><i>//</i></h3><ul><li>băng tần thường dân (để lái xe có thể liên hệ với nhau trong khoảng</li></ul>","description":"băng tần thường dân (để lái xe có thể liên hệ với nhau trong khoảng","pronounce":""},{"id":7993,"word":"citizenship","html":"<h1>citizenship</h1><h3><i>/'sitiznʃip/</i></h3><h2>danh từ</h2><ul><li>tư cách công dân</li><li>quyền công dân</li><li>bổn phận công dân</li></ul>","description":"danh từ: tư cách công dân","pronounce":"'sitiznʃip"},{"id":72647,"word":"citral","html":"<h1>citral</h1><h3><i>//</i></h3>* danh từ<br/><ul><li>(hoá học) xitrala</li></ul>","description":"(hoá học) xitrala","pronounce":""},{"id":72648,"word":"citrate","html":"<h1>citrate</h1><h3><i>//</i></h3>* danh từ<br/><ul><li>một loại muối của axit citric</li></ul>","description":"một loại muối của axit citric","pronounce":""},{"id":7994,"word":"citric","html":"<h1>citric</h1><h3><i>/'sitrik/</i></h3><h2>tính từ</h2><ul><li>(hoá học) xitric<ul style=\"list-style-type:circle\"><li>citric acid:<i> axit xitric</i></li></ul></li></ul>","description":"tính từ: (hoá học) xitric","pronounce":"'sitrik"},{"id":72649,"word":"citric acid","html":"<h1>citric acid</h1><h3><i>//</i></h3>* danh từ<br/><ul><li>(hóa) axitxitric</li></ul>","description":"(hóa) axitxitric","pronounce":""},{"id":72650,"word":"citriculture","html":"<h1>citriculture</h1><h3><i>//</i></h3>* danh từ<br/><ul><li>nghề trồng chanh, cam quýt</li></ul>","description":"nghề trồng chanh, cam quýt","pronounce":""},{"id":7995,"word":"citrine","html":"<h1>citrine</h1><h3><i>/si'trin/</i></h3><h2>tính từ</h2><ul><li>màu vỏ chanh</li></ul><h2>danh từ</h2><ul><li>(khoáng chất) Xitrin</li></ul>","description":"tính từ: màu vỏ chanh","pronounce":"si'trin"},{"id":7996,"word":"citron","html":"<h1>citron</h1><h3><i>/'sitrən/</i></h3><h2>danh từ</h2><ul><li>(thực vật học) cây thanh yên</li><li>quả thanh yên</li><li>màu vỏ chanh ((cũng) citron colour)</li></ul>","description":"danh từ: (thực vật học) cây thanh yên","pronounce":"'sitrən"},{"id":7997,"word":"citronella","html":"<h1>citronella</h1><h3><i>/,sitrə'nelə/</i></h3><h2>danh từ</h2><ul><li>(thực vật học) cây xả</li><li>dầu xả</li></ul>","description":"danh từ: (thực vật học) cây xả","pronounce":",sitrə'nelə"},{"id":7998,"word":"citrus","html":"<h1>citrus</h1><h3><i>/'sitrəs/</i></h3><h2>danh từ</h2><ul><li>(thực vật học) giống cam quít</li></ul>","description":"danh từ: (thực vật học) giống cam quít","pronounce":"'sitrəs"},{"id":7999,"word":"city","html":"<h1>city</h1><h3><i>/'siti/</i></h3><h2>danh từ</h2><ul><li>thành phố, thành thị, đô thị</li><li>dân thành thị</li><li>(the City) trung tâm thương nghiệp và tài chính thành phố Luân-đôn</li><li>(định ngữ) (thuộc) thành phố</li><li>(City) (định ngữ) a City man người kinh doanh,  a City article bài báo bàn về tài chính và thương nghiệp,  City editor người biên tập phụ trách tin tức về tài chính (trong một tờ báo)</li></ul><h2>thành ngữ</h2><ol><li>Celestial City</li><li>Heavenly City</li><li>City of God<ul><li>thiên đường</li></ul></li><li>city state<ul><li>thành phố độc lập và có chủ quyền (như một nước)</li></ul></li></ol>","description":"danh từ: thành phố, thành thị, đô thị","pronounce":"'siti"},{"id":72651,"word":"city editor","html":"<h1>city editor</h1><h3><i>//</i></h3><ul><li>(anh) nhà báo chịu trách nhiệm về tin tức tài chính (trên một tờ báo)</li><li>(Mỹ) nhà báo chịu trách nhiệm  về tin tức địa phương</li></ul>","description":"(anh) nhà báo chịu trách nhiệm về tin tức tài chính (trên một tờ báo)","pronounce":""},{"id":72652,"word":"city hall","html":"<h1>city hall</h1><h3><i>//</i></h3><ul><li>tòa thị chính thành phố lớn</li></ul>","description":"tòa thị chính thành phố lớn","pronounce":""},{"id":72653,"word":"city-father","html":"<h1>city-father</h1><h3><i>//</i></h3>* danh từ<br/><ul><li>người cha của đô thị (người có uy tín rất lớn trong đô thị)</li></ul>","description":"người cha của đô thị (người có uy tín rất lớn trong đô thị)","pronounce":""},{"id":72654,"word":"city-hall","html":"<h1>city-hall</h1><h3><i>//</i></h3>* danh từ<br/><ul><li>toà thị chính của thành phố; cơ quan quản lý thành phố</li></ul>","description":"toà thị chính của thành phố; cơ quan quản lý thành phố","pronounce":""},{"id":72655,"word":"city-manager","html":"<h1>city-manager</h1><h3><i>//</i></h3>* danh từ<br/><ul><li>ủy viên hội đồng thành phố lo quản lý thành phố</li></ul>","description":"ủy viên hội đồng thành phố lo quản lý thành phố","pronounce":""},{"id":72656,"word":"city-planning","html":"<h1>city-planning</h1><h3><i>//</i></h3>* danh từ<br/><ul><li>việc kế hoạch hoá thành phố / đô thị</li></ul>","description":"việc kế hoạch hoá thành phố / đô thị","pronounce":""},{"id":72657,"word":"city-scape","html":"<h1>city-scape</h1><h3><i>//</i></h3>* danh từ<br/><ul><li>quang cảnh thành phố/đô thị</li><li>bức ảnh quang cảnh đô thị</li></ul>","description":"quang cảnh thành phố/đô thị","pronounce":""},{"id":72658,"word":"city-state","html":"<h1>city-state</h1><h3><i>//</i></h3><ul><li>thành quốc</li></ul>","description":"thành quốc","pronounce":""},{"id":8000,"word":"civet","html":"<h1>civet</h1><h3><i>/'sivit/</i></h3><h2>danh từ</h2><ul><li>(động vật học) con cầy hương ((cũng) civet cat)</li><li>chất xạ hương</li></ul>","description":"danh từ: (động vật học) con cầy hương ((cũng) civet cat)","pronounce":"'sivit"},{"id":8001,"word":"civic","html":"<h1>civic</h1><h3><i>/'sivik/</i></h3><h2>tính từ</h2><ul><li>(thuộc) công dân<ul style=\"list-style-type:circle\"><li>civic rights:<i> quyền công dân</i></li><li>civic duty:<i> bổn phận công dân</i></li></ul></li></ul><h2>thành ngữ</h2><ol><li>civic guard<ul><li>cảnh sát (ở Ai-len)</li></ul></li></ol>","description":"tính từ: (thuộc) công dân","pronounce":"'sivik"},{"id":72659,"word":"civics","html":"<h1>civics</h1><h3><i>//</i></h3>* danh từ<br/><ul><li>khoa nghiên cứu quyền lợi và bổn phận công dân</li></ul>","description":"khoa nghiên cứu quyền lợi và bổn phận công dân","pronounce":""},{"id":8002,"word":"civil","html":"<h1>civil</h1><h3><i>/'sivl/</i></h3><h2>tính từ</h2><ul><li>(thuộc) công dân<ul style=\"list-style-type:circle\"><li>civil rights:<i> quyền công dân</i></li></ul></li><li>(thuộc) thường dân (trái với quân đội)</li><li>(thuộc) bên đời (trái với bên đạo)<ul style=\"list-style-type:circle\"><li>civil marriage:<i> cuộc kết hôn không theo lễ nghi tôn giáo</i></li></ul></li><li>(pháp lý) hộ (thuộc) dân sự (trái với hình)<ul style=\"list-style-type:circle\"><li>civil law:<i> luật hộ, luật dân sự</i></li></ul></li><li>lễ phép, lễ độ, lịch sự</li><li>thường<ul style=\"list-style-type:circle\"><li>civil day:<i> ngày thường (trái với ngày thiên văn)</i></li></ul></li></ul><h2>thành ngữ</h2><ol><li>Civil Defence<ul><li>tổ chức phòng không nhân dân</li></ul></li><li>civil disobedience<ul><li>(Ân) phong trào chống thuế, chống luật pháp</li></ul></li><li>civil list<ul><li>tiền nghị viện cấp cho nhà vua Anh</li></ul></li><li>to keep a civil tongue in one's head<ul><li>giữ lễ phép, giữ lễ độ</li></ul></li></ol>","description":"tính từ: (thuộc) công dân","pronounce":"'sivl"},{"id":72660,"word":"civil marriage","html":"<h1>civil marriage</h1><h3><i>//</i></h3><ul><li>hôn nhân theo thủ tục bên đời (không có lễ tôn giáo)</li></ul>","description":"hôn nhân theo thủ tục bên đời (không có lễ tôn giáo)","pronounce":""},{"id":8003,"word":"civil rights","html":"<h1>civil rights</h1><h3><i>/'sivil'raits/</i></h3><h2>danh từ (từ Mỹ,nghĩa Mỹ)</h2><ul><li>quyền tự do cá nhân (cho một cá nhân hay một nhóm thiểu số)</li><li>quyền bình đẳng cho người da đen</li><li>quyền công dân</li></ul>","description":"danh từ (từ Mỹ,nghĩa Mỹ): quyền tự do cá nhân (cho một cá nhân hay một nhóm thiểu số)","pronounce":"'sivil'raits"},{"id":8004,"word":"civil servant","html":"<h1>civil servant</h1><h3><i>/'sivil'sə:vənt/</i></h3><h2>danh từ</h2><ul><li>công chức</li></ul>","description":"danh từ: công chức","pronounce":"'sivil'sə:vənt"},{"id":8005,"word":"civil service","html":"<h1>civil service</h1><h3><i>/'sivil'sə:vis/</i></h3><h2>danh từ</h2><ul><li>ngành dân chính</li><li>công chức ngành dân chính</li><li>phương pháp tuyển dụng công chức (qua kỳ thi)</li></ul>","description":"danh từ: ngành dân chính","pronounce":"'sivil'sə:vis"},{"id":8006,"word":"civil war","html":"<h1>civil war</h1><h3><i>/'sivlwɔ:/</i></h3><h2>danh từ</h2><ul><li>nội chiến</li></ul>","description":"danh từ: nội chiến","pronounce":"'sivlwɔ:"},{"id":72661,"word":"civil-law","html":"<h1>civil-law</h1><h3><i>//</i></h3><ul><li>luật dân sự, luật hộ</li></ul>","description":"luật dân sự, luật hộ","pronounce":""},{"id":8007,"word":"civil-spoken","html":"<h1>civil-spoken</h1><h3><i>/'sivl'spoukn/</i></h3><h2>tính từ</h2><ul><li>lịch sự, phong nhã, nhã nhặn, có lễ độ (ăn nói)</li></ul>","description":"tính từ: lịch sự, phong nhã, nhã nhặn, có lễ độ (ăn nói)","pronounce":"'sivl'spoukn"},{"id":8008,"word":"civilian","html":"<h1>civilian</h1><h3><i>/'siviljən/</i></h3><h2>danh từ</h2><ul><li>người thường, thường dân</li></ul><h2>tính từ</h2><ul><li>(thuộc) thường dân (trái với quân đội)<ul style=\"list-style-type:circle\"><li>civilian clothes:<i> quần áo thường</i></li><li>civilian population:<i> thường dân</i></li></ul></li></ul>","description":"danh từ: người thường, thường dân","pronounce":"'siviljən"},{"id":72662,"word":"civilianization","html":"<h1>civilianization</h1><h3><i>//</i></h3><ul><li>xem civilianize</li></ul>","description":"xem civilianize","pronounce":""},{"id":8009,"word":"civilianize","html":"<h1>civilianize</h1><h3><i>/si'viljənaiz/</i></h3><h2>ngoại động từ</h2><ul><li>dân sự hoá</li></ul>","description":"ngoại động từ: dân sự hoá","pronounce":"si'viljənaiz"},{"id":72663,"word":"civilisation","html":"<h1>civilisation</h1><h3><i>//</i></h3>* danh từ<br/><ul><li>sự làm cho văn minh, sự khai hoá</li><li>nền văn minh</li><li>những nước văn minh, những dân tộc văn minh</li></ul>","description":"sự làm cho văn minh, sự khai hoá","pronounce":""},{"id":8010,"word":"civilise","html":"<h1>civilise</h1><h3><i>/'sivilaiz/</i></h3><h2>ngoại động từ</h2><ul><li>làm cho văn minh, truyền bá văn minh, khai hoá, giáo hoá</li></ul><h2>thành ngữ</h2><ol><li>to civilize away<ul><li>bài trừ (hủ tục...)</li></ul></li></ol>","description":"ngoại động từ: làm cho văn minh, truyền bá văn minh, khai hoá, giáo hoá","pronounce":"'sivilaiz"},{"id":8011,"word":"civility","html":"<h1>civility</h1><h3><i>/si'viliti/</i></h3><h2>danh từ</h2><ul><li>sự lễ độ, phép lịch sự</li></ul>","description":"danh từ: sự lễ độ, phép lịch sự","pronounce":"si'viliti"},{"id":8012,"word":"civilizable","html":"<h1>civilizable</h1><h3><i>/'sivilaizəbl/</i></h3><h2>tính từ</h2><ul><li>có thể khai hoá, có thể làm cho văn minh</li></ul>","description":"tính từ: có thể khai hoá, có thể làm cho văn minh","pronounce":"'sivilaizəbl"},{"id":8013,"word":"civilization","html":"<h1>civilization</h1><h3><i>/,sivilai'zeiʃn/</i></h3><h2>danh từ</h2><ul><li>sự làm cho văn minh, sự khai hoá</li><li>nền văn minh<ul style=\"list-style-type:circle\"><li>the civilization of mankind:<i> nền văn minh của loài người</i></li></ul></li><li>những nước văn minh, những dân tộc văn minh</li></ul>","description":"danh từ: sự làm cho văn minh, sự khai hoá","pronounce":",sivilai'zeiʃn"},{"id":8014,"word":"civilize","html":"<h1>civilize</h1><h3><i>/'sivilaiz/</i></h3><h2>ngoại động từ</h2><ul><li>làm cho văn minh, truyền bá văn minh, khai hoá, giáo hoá</li></ul><h2>thành ngữ</h2><ol><li>to civilize away<ul><li>bài trừ (hủ tục...)</li></ul></li></ol>","description":"ngoại động từ: làm cho văn minh, truyền bá văn minh, khai hoá, giáo hoá","pronounce":"'sivilaiz"},{"id":72664,"word":"civilized","html":"<h1>civilized</h1><h3><i>//</i></h3>* tính từ<br/><ul><li>văn minh</li><li>khai hoá</li><li>lễ phép; lịch sự</li></ul>","description":"văn minh","pronounce":""},{"id":8015,"word":"civilizer","html":"<h1>civilizer</h1><h3><i>/'sivilaizə/</i></h3><h2>danh từ</h2><ul><li>người truyền bá văn minh, người khai hoá</li></ul>","description":"danh từ: người truyền bá văn minh, người khai hoá","pronounce":"'sivilaizə"},{"id":72665,"word":"civilly","html":"<h1>civilly</h1><h3><i>//</i></h3>* phó từ<br/><ul><li>lịch sự, nhã nhặn</li></ul>","description":"lịch sự, nhã nhặn","pronounce":""},{"id":8016,"word":"civvy","html":"<h1>civvy</h1><h3><i>/'sivi/</i></h3><h2>danh từ</h2><ul><li>(từ lóng) người thường, thường dân (trái với quân đội)</li><li>(số nhiều) (quân sự) quần áo thường (trái với quần áo bộ đội)</li></ul><h2>thành ngữ</h2><ol><li>civy street<ul><li>(quân sự),  (từ lóng) đời sống thường dân, sinh hoạt thường dân (trái với sinh hoạt trong quân đội)</li></ul></li></ol>","description":"danh từ: (từ lóng) người thường, thường dân (trái với quân đội)","pronounce":"'sivi"},{"id":8017,"word":"civy","html":"<h1>civy</h1><h3><i>/'sivi/</i></h3><h2>danh từ</h2><ul><li>(từ lóng) người thường, thường dân (trái với quân đội)</li><li>(số nhiều) (quân sự) quần áo thường (trái với quần áo bộ đội)</li></ul><h2>thành ngữ</h2><ol><li>civy street<ul><li>(quân sự),  (từ lóng) đời sống thường dân, sinh hoạt thường dân (trái với sinh hoạt trong quân đội)</li></ul></li></ol>","description":"danh từ: (từ lóng) người thường, thường dân (trái với quân đội)","pronounce":"'sivi"}]