[{"id":64848,"word":"Dickey fuller test","html":"<h1>Dickey fuller test</h1><h3><i>//</i></h3><ul><li>(Econ) Các kiểm định Dickey Fuller.+ Một tập hợp các kiểm định sự tồn tại của đơn vị gốc trong chuỗi thời gian.<br/></li></ul>","description":"(Econ) Các kiểm định Dickey Fuller.","pronounce":""},{"id":75667,"word":"dicast","html":"<h1>dicast</h1><h3><i>//</i></h3>* danh từ<br/><ul><li>người trong số 6000 người dân cổ Aten được chọn để tham dự việc xét xử</li></ul>","description":"người trong số 6000 người dân cổ Aten được chọn để tham dự việc xét xử","pronounce":""},{"id":12417,"word":"dice","html":"<h1>dice</h1><h3><i>/dais/</i></h3><h2>danh từ</h2><ul><li>số nhiều của die</li><li>trò chơi súc sắc</li></ul><h2>ngoại động từ (:<i> way)</i></h2><ul><li>đánh súc sắc thua sạch<ul style=\"list-style-type:circle\"><li>to dice away one's fortune:<i> đánh súc sắc thua sạch tài sản</i></li></ul></li><li>kẻ ô vuông, vạch ô vuông (trên vải)</li><li>thái (thịt...) hạt lựu</li></ul>","description":"danh từ: số nhiều của die","pronounce":"dais"},{"id":104848,"word":"dice","html":"<h1>dice</h1><h3><i>//</i></h3><ul><li>(lý thuyết trò chơi) quân (hạt) súc sắc; trò chơi xúc sắc</li></ul>","description":"(lý thuyết trò chơi) quân (hạt) súc sắc; trò chơi xúc sắc","pronounce":""},{"id":12418,"word":"dice-box","html":"<h1>dice-box</h1><h3><i>/'daisbɔks/</i></h3><h2>danh từ</h2><ul><li>cốc gieo súc sắc</li></ul>","description":"danh từ: cốc gieo súc sắc","pronounce":"'daisbɔks"},{"id":75668,"word":"dicephalous","html":"<h1>dicephalous</h1><h3><i>//</i></h3>* danh từ<br/><ul><li>động vật hai đầu</li></ul>","description":"động vật hai đầu","pronounce":""},{"id":12419,"word":"dicer","html":"<h1>dicer</h1><h3><i>/'daisə/</i></h3><h2>danh từ</h2><ul><li>người đánh súc sắc</li></ul>","description":"danh từ: người đánh súc sắc","pronounce":"'daisə"},{"id":75669,"word":"dicey","html":"<h1>dicey</h1><h3><i>//</i></h3>* tính từ<br/><ul><li>nguy hiểm</li></ul>","description":"nguy hiểm","pronounce":""},{"id":75670,"word":"dichasium","html":"<h1>dichasium</h1><h3><i>//</i></h3>* danh từ<br/><ul><li>số nhiều dichasia</li><li>xim hai ngã</li></ul>","description":"số nhiều dichasia","pronounce":""},{"id":12420,"word":"dichgamous","html":"<h1>dichgamous</h1><h3><i>/di'kɔgəməs/</i></h3><h2>tính từ</h2><ul><li>(thực vật học) chín khác lúc (nhị, nhuỵ)</li></ul>","description":"tính từ: (thực vật học) chín khác lúc (nhị, nhuỵ)","pronounce":"di'kɔgəməs"},{"id":12421,"word":"dichgamy","html":"<h1>dichgamy</h1><h3><i>/di'kɔgəmi/</i></h3><h2>danh từ</h2><ul><li>(thực vật học) sự chín khác lúc (nhị, nhuỵ)</li></ul>","description":"danh từ: (thực vật học) sự chín khác lúc (nhị, nhuỵ)","pronounce":"di'kɔgəmi"},{"id":75671,"word":"dichlamydeous","html":"<h1>dichlamydeous</h1><h3><i>//</i></h3>* tính từ<br/><ul><li>có bao hoa kép</li></ul>","description":"có bao hoa kép","pronounce":""},{"id":12422,"word":"dichloride","html":"<h1>dichloride</h1><h3><i>/dai'klɔ:raid/</i></h3><h2>danh từ</h2><ul><li>(hoá học) điclorua</li></ul>","description":"danh từ: (hoá học) điclorua","pronounce":"dai'klɔ:raid"},{"id":75672,"word":"dichlorobenzene","html":"<h1>dichlorobenzene</h1><h3><i>//</i></h3>* danh từ<br/><ul><li>(hoá học) điclorobenzen</li></ul>","description":"(hoá học) điclorobenzen","pronounce":""},{"id":75673,"word":"dichogamous","html":"<h1>dichogamous</h1><h3><i>//</i></h3>* tính từ<br/><ul><li>chín khác lúc (nhị,  nhụy); biệt giao</li></ul>","description":"chín khác lúc (nhị,  nhụy); biệt giao","pronounce":""},{"id":75674,"word":"dichogamy","html":"<h1>dichogamy</h1><h3><i>//</i></h3>* danh từ<br/><ul><li>tính chín khác lúc (nhị,  nhụy)</li></ul>","description":"tính chín khác lúc (nhị,  nhụy)","pronounce":""},{"id":12423,"word":"dichotomic","html":"<h1>dichotomic</h1><h3><i>/,dikou'tɔmik/</i></h3><h2>tính từ</h2><ul><li>phân đôi, rẽ đôi</li></ul>","description":"tính từ: phân đôi, rẽ đôi","pronounce":",dikou'tɔmik"},{"id":104849,"word":"dichotomic","html":"<h1>dichotomic</h1><h3><i>//</i></h3><ul><li>lưỡng phân</li></ul>","description":"lưỡng phân","pronounce":""},{"id":12424,"word":"dichotomise","html":"<h1>dichotomise</h1><h3><i>/di'kɔtəmaiz/</i></h3><h2>động từ</h2><ul><li>phản đối, rẽ đôi</li></ul>","description":"động từ: phản đối, rẽ đôi","pronounce":"di'kɔtəmaiz"},{"id":75675,"word":"dichotomization","html":"<h1>dichotomization</h1><h3><i>//</i></h3>* danh từ<br/><ul><li>sự lưỡng phân; sự phân đôi</li></ul>","description":"sự lưỡng phân; sự phân đôi","pronounce":""},{"id":12425,"word":"dichotomize","html":"<h1>dichotomize</h1><h3><i>/di'kɔtəmaiz/</i></h3><h2>động từ</h2><ul><li>phản đối, rẽ đôi</li></ul>","description":"động từ: phản đối, rẽ đôi","pronounce":"di'kɔtəmaiz"},{"id":12426,"word":"dichotomous","html":"<h1>dichotomous</h1><h3><i>/di'kɔtəməs/</i></h3><h2>tính từ</h2><ul><li>phân đôi, rẽ đôi</li></ul>","description":"tính từ: phân đôi, rẽ đôi","pronounce":"di'kɔtəməs"},{"id":104850,"word":"dichotomous","html":"<h1>dichotomous</h1><h3><i>//</i></h3><ul><li>lưỡng phân</li></ul>","description":"lưỡng phân","pronounce":""},{"id":12427,"word":"dichotomy","html":"<h1>dichotomy</h1><h3><i>/di'kɔtəmi/</i></h3><h2>danh từ</h2><ul><li>sự phân đôi, sự rẽ đôi</li><li>tuần trăng nửa vành</li></ul>","description":"danh từ: sự phân đôi, sự rẽ đôi","pronounce":"di'kɔtəmi"},{"id":104851,"word":"dichotomy","html":"<h1>dichotomy</h1><h3><i>//</i></h3><ul><li>phép lưỡng phân</li><li>binomial d. lưỡng phân nhị thức</li></ul>","description":"phép lưỡng phân","pronounce":""},{"id":12428,"word":"dichroic","html":"<h1>dichroic</h1><h3><i>/dai'krouik/</i></h3><h2>tính từ</h2><ul><li>toả hai sắc, lưỡng hướng sắc</li></ul>","description":"tính từ: toả hai sắc, lưỡng hướng sắc","pronounce":"dai'krouik"},{"id":12429,"word":"dichroism","html":"<h1>dichroism</h1><h3><i>/dai'krouizm/</i></h3><h2>danh từ</h2><ul><li>tính toả hai sắc, tính lưỡng hướng sắc</li></ul>","description":"danh từ: tính toả hai sắc, tính lưỡng hướng sắc","pronounce":"dai'krouizm"},{"id":12430,"word":"dichromate","html":"<h1>dichromate</h1><h3><i>/dai'koumit/</i></h3><h2>danh từ</h2><ul><li>(hoá học) đicromat</li></ul>","description":"danh từ: (hoá học) đicromat","pronounce":"dai'koumit"},{"id":104852,"word":"dichromate","html":"<h1>dichromate</h1><h3><i>//</i></h3><ul><li>(tô pô) lưỡng sắc</li></ul>","description":"(tô pô) lưỡng sắc","pronounce":""},{"id":12431,"word":"dichromatic","html":"<h1>dichromatic</h1><h3><i>/,daikrou'mætik/</i></h3><h2>tính từ</h2><ul><li>có hai sắc, có hai màu gốc</li></ul>","description":"tính từ: có hai sắc, có hai màu gốc","pronounce":",daikrou'mætik"},{"id":104853,"word":"dichromatic","html":"<h1>dichromatic</h1><h3><i>//</i></h3><ul><li>có lưỡng sắc</li></ul>","description":"có lưỡng sắc","pronounce":""},{"id":12432,"word":"dichromatism","html":"<h1>dichromatism</h1><h3><i>/'daikroumətizm/</i></h3><h2>danh từ</h2><ul><li>tính hai sắc, tính hai màu gốc</li></ul>","description":"danh từ: tính hai sắc, tính hai màu gốc","pronounce":"'daikroumətizm"},{"id":104854,"word":"dichromatism","html":"<h1>dichromatism</h1><h3><i>//</i></h3><ul><li>(tô pô) tính lưỡng sắc</li></ul>","description":"(tô pô) tính lưỡng sắc","pronounce":""},{"id":75676,"word":"dichromatopsia","html":"<h1>dichromatopsia</h1><h3><i>//</i></h3>* danh từ<br/><ul><li>(sinh học) sự nhìn màu kép</li></ul>","description":"(sinh học) sự nhìn màu kép","pronounce":""},{"id":12433,"word":"dichromic","html":"<h1>dichromic</h1><h3><i>/dai'kroumik/</i></h3><h2>tính từ</h2><ul><li>chỉ hai màu, chỉ phân biệt được hai màu gốc (đặc biệt là đối với người mù màu)</li></ul>","description":"tính từ: chỉ hai màu, chỉ phân biệt được hai màu gốc (đặc biệt là đối với người mù màu)","pronounce":"dai'kroumik"},{"id":12434,"word":"dick","html":"<h1>dick</h1><h3><i>/dik/</i></h3><h2>danh từ,  (từ lóng)</h2><ul><li>to take one's dick that thề rằng, quả quyết rằng</li><li>up to dick xuất sắc, phi thường, cừ khôi</li></ul><h2>danh từ</h2><ul><li>(từ Mỹ,nghĩa Mỹ),  (từ lóng) mật thám, thám tử</li></ul>","description":"danh từ,  (từ lóng): to take one's dick that thề rằng, quả quyết rằng","pronounce":"dik"},{"id":12435,"word":"dickens","html":"<h1>dickens</h1><h3><i>/'dikinz/</i></h3><h2>danh từ</h2><ul><li>(thông tục), ma, quỷ<ul style=\"list-style-type:circle\"><li>what the dickens did you go there for?:<i> cậu đến đó làm cái quỷ gì?</i></li></ul></li></ul>","description":"danh từ: (thông tục), ma, quỷ","pronounce":"'dikinz"},{"id":75677,"word":"dickensian","html":"<h1>dickensian</h1><h3><i>//</i></h3>* tính từ<br/><ul><li>giống như truyện của Dickens mô tả</li></ul>","description":"giống như truyện của Dickens mô tả","pronounce":""},{"id":12436,"word":"dicker","html":"<h1>dicker</h1><h3><i>/'dikə/</i></h3><h2>danh từ</h2><ul><li>(thương nghiệp), một chục, mười (thường là bộ da)</li></ul><h2>nội động từ</h2><ul><li>(từ Mỹ,nghĩa Mỹ) mặc cả</li><li>đổi chác</li></ul>","description":"danh từ: (thương nghiệp), một chục, mười (thường là bộ da)","pronounce":"'dikə"},{"id":12437,"word":"dickey","html":"<h1>dickey</h1><h3><i>/'diki/</i></h3><h2>danh từ</h2><ul><li>con lừa, con lừa con</li><li>con chim con ((cũng) dickey bird)</li><li>yếm giả (của áo sơ mi)</li><li>cái tạp dề</li><li>ghế ngồi của người đánh xe</li><li>ghế ngồi của người hầu (ở phía sau xe); (từ Mỹ,nghĩa Mỹ) chỗ ngồi đằng sau xe (ôtô)</li></ul>","description":"danh từ: con lừa, con lừa con","pronounce":"'diki"},{"id":75678,"word":"dickeybird","html":"<h1>dickeybird</h1><h3><i>//</i></h3>* danh từ<br/><ul><li>(thông tục) con chim con</li><li>chỉ một lời<ul style=\"list-style-type:circle\"><li> never said a dickeybird:<i>không bao giờ nói dù chỉ một lời</i></li></ul></li></ul>","description":"(thông tục) con chim con","pronounce":""},{"id":12438,"word":"dicky","html":"<h1>dicky</h1><h3><i>/'diki/</i></h3><h2>danh từ</h2><ul><li>con lừa, con lừa con</li><li>con chim con ((cũng) dickey bird)</li><li>yếm giả (của áo sơ mi)</li><li>cái tạp dề</li><li>ghế ngồi của người đánh xe</li><li>ghế ngồi của người hầu (ở phía sau xe); (từ Mỹ,nghĩa Mỹ) chỗ ngồi đằng sau xe (ôtô)</li></ul>","description":"danh từ: con lừa, con lừa con","pronounce":"'diki"},{"id":75679,"word":"diclinous","html":"<h1>diclinous</h1><h3><i>//</i></h3>* tính từ<br/><ul><li>(thực vật học) Có hoa đực hoa cái trên cùng một cây</li></ul>","description":"(thực vật học) Có hoa đực hoa cái trên cùng một cây","pronounce":""},{"id":75680,"word":"dicoccus","html":"<h1>dicoccus</h1><h3><i>//</i></h3>* tính từ<br/><ul><li>Có quả hạch kép</li></ul>","description":"Có quả hạch kép","pronounce":""},{"id":75681,"word":"dicot","html":"<h1>dicot</h1><h3><i>//</i></h3>* danh từ<br/><ul><li>xem decotylendon</li></ul>","description":"xem decotylendon","pronounce":""},{"id":75682,"word":"dicotyl","html":"<h1>dicotyl</h1><h3><i>//</i></h3>* danh từ<br/><ul><li>xem dicotylendon</li></ul>","description":"xem dicotylendon","pronounce":""},{"id":12439,"word":"dicotyledon","html":"<h1>dicotyledon</h1><h3><i>/'dai,kɔti'li:dən/</i></h3><h2>danh từ</h2><ul><li>(thực vật học) cây hai lá mầm</li></ul>","description":"danh từ: (thực vật học) cây hai lá mầm","pronounce":"'dai,kɔti'li:dən"},{"id":12440,"word":"dicotyledonous","html":"<h1>dicotyledonous</h1><h3><i>/'dai,kɔti'li:dənəs/</i></h3><h2>tính từ</h2><ul><li>(thực vật học) có hai lá mầm</li></ul>","description":"tính từ: (thực vật học) có hai lá mầm","pronounce":"'dai,kɔti'li:dənəs"},{"id":75683,"word":"dicratic","html":"<h1>dicratic</h1><h3><i>//</i></h3>* tính từ<br/><ul><li>(thực vật học) Bộ bốn bào tử lưỡng tính</li></ul>","description":"(thực vật học) Bộ bốn bào tử lưỡng tính","pronounce":""},{"id":75684,"word":"dicrotic","html":"<h1>dicrotic</h1><h3><i>//</i></h3>* tính từ<br/><ul><li>(Y học) Thuộc mạch đập đôi</li></ul>","description":"(Y học) Thuộc mạch đập đôi","pronounce":""},{"id":75685,"word":"dicrotism","html":"<h1>dicrotism</h1><h3><i>//</i></h3>* danh từ<br/><ul><li>Hiện tượng mạch đập đôi</li></ul>","description":"Hiện tượng mạch đập đôi","pronounce":""},{"id":12441,"word":"dicta","html":"<h1>dicta</h1><h3><i>/'diktəm/</i></h3><h2>danh từ,  số nhiều dicta,  dictums</h2><ul><li>lời quả quyết, lời tuyên bố chính thức</li><li>(pháp lý) lời phát biểu ý kiến của quan toà (không có giá trị pháp lý)</li><li>châm ngôn</li></ul>","description":"danh từ,  số nhiều dicta,  dictums: lời quả quyết, lời tuyên bố chính thức","pronounce":"'diktəm"},{"id":75686,"word":"dictagraph","html":"<h1>dictagraph</h1><h3><i>//</i></h3><ul><li>xem dictograph</li></ul>","description":"xem dictograph","pronounce":""},{"id":12442,"word":"dictaphone","html":"<h1>dictaphone</h1><h3><i>/'diktəfoun/</i></h3><h2>danh từ</h2><ul><li>máy ghi tiếng</li></ul>","description":"danh từ: máy ghi tiếng","pronounce":"'diktəfoun"},{"id":12443,"word":"dictate","html":"<h1>dictate</h1><h3><i>/dik'teit/</i></h3><h2>danh từ</h2><ul><li>((thường) số nhiều) mệnh lệnh, tiếng gọi<ul style=\"list-style-type:circle\"><li>the dictates of conscience:<i> tiếng gọi của lương tâm</i></li><li>the dictates of reason:<i> tiếng gọi của lý trí</i></li></ul></li><li>(chính trị) sự bức chế</li></ul><h2>ngoại động từ</h2><ul><li>đọc cho viết, đọc chính tả</li><li>ra (lệnh, điều kiện...)</li></ul><h2>nội động từ</h2><ul><li>sai khiến, ra lệnh</li><li>bức chế</li></ul>","description":"danh từ: ((thường) số nhiều) mệnh lệnh, tiếng gọi","pronounce":"dik'teit"},{"id":104855,"word":"dictating","html":"<h1>dictating</h1><h3><i>//</i></h3><ul><li>(máy tính) đọc để viết, viết chính tả</li></ul>","description":"(máy tính) đọc để viết, viết chính tả","pronounce":""},{"id":12444,"word":"dictation","html":"<h1>dictation</h1><h3><i>/dik'teiʃn/</i></h3><h2>danh từ</h2><ul><li>sự đọc cho viết, sự đọc chính tả<ul style=\"list-style-type:circle\"><li>to write at somebody's dictation:<i> viết theo ai đọc</i></li></ul></li><li>bái chính tả</li><li>sự sai khiến, sự ra lệnh<ul style=\"list-style-type:circle\"><li>to do something at somebody's dictation:<i> làm việc gì theo sự sai khiến của ai, làm việc gì theo lệnh của ai</i></li></ul></li><li>(như) dictate</li></ul>","description":"danh từ: sự đọc cho viết, sự đọc chính tả","pronounce":"dik'teiʃn"},{"id":12445,"word":"dictator","html":"<h1>dictator</h1><h3><i>/dik'teitə/</i></h3><h2>danh từ</h2><ul><li>kẻ độc tài; người có quyền hành tuyệt đối (ở một lĩnh vực nào)</li><li>người đọc cho (người khác) viết, người đọc chính tả</li></ul>","description":"danh từ: kẻ độc tài; người có quyền hành tuyệt đối (ở một lĩnh vực nào)","pronounce":"dik'teitə"},{"id":12446,"word":"dictatorial","html":"<h1>dictatorial</h1><h3><i>/,diktə'tɔ:riəl/</i></h3><h2>tính từ</h2><ul><li>độc tài<ul style=\"list-style-type:circle\"><li>a dictatorial regime:<i> một chế độ độc tài</i></li></ul></li></ul>","description":"tính từ: độc tài","pronounce":",diktə'tɔ:riəl"},{"id":75687,"word":"dictatorially","html":"<h1>dictatorially</h1><h3><i>//</i></h3>* phó từ<br/><ul><li>độc tài, độc đoán</li></ul>","description":"độc tài, độc đoán","pronounce":""},{"id":75688,"word":"dictatorialness","html":"<h1>dictatorialness</h1><h3><i>//</i></h3>* danh từ<br/><ul><li>xem dictatorial, chỉ chế độ, chính thể, sự</li></ul>","description":"xem dictatorial, chỉ chế độ, chính thể, sự","pronounce":""},{"id":12447,"word":"dictatorship","html":"<h1>dictatorship</h1><h3><i>/dik'teitəʃip/</i></h3><h2>danh từ</h2><ul><li>chế độ độc tài; nền chuyên chính<ul style=\"list-style-type:circle\"><li>dictatorship of the prolerarian:<i> nền chuyên chính vô sản</i></li></ul></li></ul>","description":"danh từ: chế độ độc tài; nền chuyên chính","pronounce":"dik'teitəʃip"},{"id":12448,"word":"dictatress","html":"<h1>dictatress</h1><h3><i>/dik'teitris/</i></h3><h2>danh từ</h2><ul><li>mụ độc tài</li></ul>","description":"danh từ: mụ độc tài","pronounce":"dik'teitris"},{"id":12449,"word":"diction","html":"<h1>diction</h1><h3><i>/'dikʃn/</i></h3><h2>danh từ</h2><ul><li>cách diễn tả, cách chọn lời, cách chọn từ (trong khi nói)</li><li>cách phát âm</li></ul>","description":"danh từ: cách diễn tả, cách chọn lời, cách chọn từ (trong khi nói)","pronounce":"'dikʃn"},{"id":75689,"word":"dictional","html":"<h1>dictional</h1><h3><i>//</i></h3>* tính từ<br/><ul><li>xem diction</li></ul>","description":"xem diction","pronounce":""},{"id":75690,"word":"dictionally","html":"<h1>dictionally</h1><h3><i>//</i></h3>* tính từ<br/><ul><li>xem diction</li></ul>","description":"xem diction","pronounce":""},{"id":12450,"word":"dictionary","html":"<h1>dictionary</h1><h3><i>/'dikʃənəri/</i></h3><h2>danh từ</h2><ul><li>từ điển<ul style=\"list-style-type:circle\"><li>a walking (living) dictionary:<i> từ điển sống, người học rộng biết nhiều</i></li></ul></li><li>(định ngữ) có tính chất từ điển, có tính chất sách vở<ul style=\"list-style-type:circle\"><li>a dictionary style:<i> văn sách vở</i></li><li>dictionary English:<i> tiếng Anh sách vở</i></li></ul></li></ul>","description":"danh từ: từ điển","pronounce":"'dikʃənəri"},{"id":104856,"word":"dictionary","html":"<h1>dictionary</h1><h3><i>//</i></h3><ul><li>từ điển</li><li>mechanical d. “từ điểm cơ giới” (để dịch bằng máy)</li></ul>","description":"từ điển","pronounce":""},{"id":12451,"word":"dictograph","html":"<h1>dictograph</h1><h3><i>/'diktəgrɑ:f/</i></h3><h2>danh từ</h2><ul><li>loa (truyền thanh)</li></ul>","description":"danh từ: loa (truyền thanh)","pronounce":"'diktəgrɑ:f"},{"id":12452,"word":"dictum","html":"<h1>dictum</h1><h3><i>/'diktəm/</i></h3><h2>danh từ,  số nhiều dicta,  dictums</h2><ul><li>lời quả quyết, lời tuyên bố chính thức</li><li>(pháp lý) lời phát biểu ý kiến của quan toà (không có giá trị pháp lý)</li><li>châm ngôn</li></ul>","description":"danh từ,  số nhiều dicta,  dictums: lời quả quyết, lời tuyên bố chính thức","pronounce":"'diktəm"},{"id":75691,"word":"dictyogen","html":"<h1>dictyogen</h1><h3><i>//</i></h3>* danh từ<br/><ul><li>(thực vật) cây có lá gân mạng lưới</li></ul>","description":"(thực vật) cây có lá gân mạng lưới","pronounce":""},{"id":75692,"word":"dictyosome","html":"<h1>dictyosome</h1><h3><i>//</i></h3>* danh từ<br/><ul><li>(sinh học) thể lưới</li></ul>","description":"(sinh học) thể lưới","pronounce":""},{"id":75693,"word":"dictyostele","html":"<h1>dictyostele</h1><h3><i>//</i></h3>* danh từ<br/><ul><li>(sinh học) trung trụ (mạng) lưới</li></ul>","description":"(sinh học) trung trụ (mạng) lưới","pronounce":""},{"id":75694,"word":"dicyclic","html":"<h1>dicyclic</h1><h3><i>//</i></h3>* tính từ<br/><ul><li>hai vòng; hai chu kỳ; hai năm</li></ul>","description":"hai vòng; hai chu kỳ; hai năm","pronounce":""},{"id":75695,"word":"dicycly","html":"<h1>dicycly</h1><h3><i>//</i></h3>* danh từ<br/><ul><li>hai vòng; hai chu kỳ; hai năm</li></ul>","description":"hai vòng; hai chu kỳ; hai năm","pronounce":""}]