[{"id":65004,"word":"EEC","html":"<h1>EEC</h1><h3><i>//</i></h3><ul><li>(Econ) Xem EUROPEAN ECONOMIC COMMUNITY</li></ul>","description":"(Econ) Xem EUROPEAN ECONOMIC COMMUNITY","pronounce":""},{"id":62536,"word":"EEROM (electrically erasable ROM)","html":"<h1>EEROM (electrically erasable ROM)</h1><h3><i>//</i></h3><ul><li>(Tech) ROM xoá bằng điện</li></ul>","description":"(Tech) ROM xoá bằng điện","pronounce":""},{"id":76799,"word":"eec","html":"<h1>eec</h1><h3><i>//</i></h3>* (viết tắt)<br/><ul><li>Cộng đồng kinh tế Âu châu (European Economic Community)</li></ul>","description":"Cộng đồng kinh tế Âu châu (European Economic Community)","pronounce":""},{"id":76800,"word":"eeg","html":"<h1>eeg</h1><h3><i>//</i></h3>* (viết tắt)<br/><ul><li>điện não đồ (electroencephalogram)</li></ul>","description":"điện não đồ (electroencephalogram)","pronounce":""},{"id":14544,"word":"eel","html":"<h1>eel</h1><h3><i>/i:l/</i></h3><h2>danh từ</h2><ul><li>con cá chình; con lươn ((nghĩa đen) & (nghĩa bóng))<ul style=\"list-style-type:circle\"><li>as slippery as an eel:<i> trơn tuột như lươn, khó nắm)</i></li></ul></li><li>(thông tục) con giun giấm</li></ul>","description":"danh từ: con cá chình; con lươn ((nghĩa đen) & (nghĩa bóng))","pronounce":"i:l"},{"id":14545,"word":"eel-basket","html":"<h1>eel-basket</h1><h3><i>/'i:l,bæskit/</i></h3>-buck)<br/>/'i:lbʌk/<br/><h2>danh từ</h2><ul><li>ống (bắt) lươn</li></ul>","description":"danh từ: ống (bắt) lươn","pronounce":"'i:l,bæskit"},{"id":14546,"word":"eel-bed","html":"<h1>eel-bed</h1><h3><i>/'i:lbed/</i></h3><h2>danh từ</h2><ul><li>ao nuôi lươn</li></ul>","description":"danh từ: ao nuôi lươn","pronounce":"'i:lbed"},{"id":14547,"word":"eel-buck","html":"<h1>eel-buck</h1><h3><i>/'i:l,bæskit/</i></h3>-buck)<br/>/'i:lbʌk/<br/><h2>danh từ</h2><ul><li>ống (bắt) lươn</li></ul>","description":"danh từ: ống (bắt) lươn","pronounce":"'i:l,bæskit"},{"id":14548,"word":"eel-grass","html":"<h1>eel-grass</h1><h3><i>/'i:lgrɑ:s/</i></h3><h2>danh từ</h2><ul><li>(thực vật học) rong lươn</li></ul>","description":"danh từ: (thực vật học) rong lươn","pronounce":"'i:lgrɑ:s"},{"id":14549,"word":"eel-pie","html":"<h1>eel-pie</h1><h3><i>/'i:lpai/</i></h3><h2>danh từ</h2><ul><li>pa-tê nóng nhồi thịt lươn</li></ul>","description":"danh từ: pa-tê nóng nhồi thịt lươn","pronounce":"'i:lpai"},{"id":14550,"word":"eel-pond","html":"<h1>eel-pond</h1><h3><i>/'i:lpɔnd/</i></h3><h2>danh từ</h2><ul><li>ao nuôi lươn</li></ul>","description":"danh từ: ao nuôi lươn","pronounce":"'i:lpɔnd"},{"id":76801,"word":"eel-shear","html":"<h1>eel-shear</h1><h3><i>//</i></h3>* danh từ<br/><ul><li>cái xiên lươn</li></ul>","description":"cái xiên lươn","pronounce":""},{"id":14551,"word":"eel-spear","html":"<h1>eel-spear</h1><h3><i>/i:lspiə/</i></h3><h2>danh từ</h2><ul><li>cái xiên lươn</li></ul>","description":"danh từ: cái xiên lươn","pronounce":"i:lspiə"},{"id":76802,"word":"eel-sucker","html":"<h1>eel-sucker</h1><h3><i>//</i></h3>* danh từ<br/><ul><li>(động vật) cá hấp đá</li></ul>","description":"(động vật) cá hấp đá","pronounce":""},{"id":14552,"word":"eel-worm","html":"<h1>eel-worm</h1><h3><i>/'i:lwə:m/</i></h3><h2>danh từ</h2><ul><li>(động vật học) giun tròn</li></ul>","description":"danh từ: (động vật học) giun tròn","pronounce":"'i:lwə:m"},{"id":76803,"word":"eelfare","html":"<h1>eelfare</h1><h3><i>//</i></h3>* danh từ<br/><ul><li>đàn cá chình con</li><li>sự di cư ngược dòng (cá chình con)</li></ul>","description":"đàn cá chình con","pronounce":""},{"id":76804,"word":"eely","html":"<h1>eely</h1><h3><i>//</i></h3>* tính từ<br/><ul><li>giống như lươn</li></ul>","description":"giống như lươn","pronounce":""},{"id":76805,"word":"eems","html":"<h1>eems</h1><h3><i>//</i></h3><ul><li>Phiên bản nâng cao của LIM EMS (Lotus-Intel-Microsoft Expanded Memory Specification), nó cho phép các trình ứng dụng DOS có thể sử dụng bộ nhớ lớn hơn 640 K Phiên bản 4 0 của EMS phù hợp với phiên bản EMS gốc lẫn phiên bản nâng cao (EEMS)</li></ul>","description":"Phiên bản nâng cao của LIM EMS (Lotus-Intel-Microsoft Expanded Memory Specification), nó cho phép các trình ứng dụng DOS có thể sử dụng bộ nhớ lớn hơn 640 K Phiên bản 4 0 của EMS phù hợp với phiên bản EMS gốc lẫn phiên bản nâng cao (EEMS)","pronounce":""},{"id":14553,"word":"eerie","html":"<h1>eerie</h1><h3><i>/'iəri/</i></h3><h2>tính từ</h2><ul><li>sợ sệt vì mê tín</li><li>kỳ lạ, kỳ quái</li></ul>","description":"tính từ: sợ sệt vì mê tín","pronounce":"'iəri"},{"id":76806,"word":"eerily","html":"<h1>eerily</h1><h3><i>//</i></h3>* phó từ<br/><ul><li>kỳ lạ, kỳ quái</li></ul>","description":"kỳ lạ, kỳ quái","pronounce":""},{"id":14554,"word":"eeriness","html":"<h1>eeriness</h1><h3><i>/'iərinis/</i></h3><h2>danh từ</h2><ul><li>sự sợ sệt vì mê tín</li><li>tính kỳ lạ, tính kỳ quái</li></ul>","description":"danh từ: sự sợ sệt vì mê tín","pronounce":"'iərinis"},{"id":14555,"word":"eery","html":"<h1>eery</h1><h3><i>/'iəri/</i></h3><h2>tính từ</h2><ul><li>sợ sệt vì mê tín</li><li>kỳ lạ, kỳ quái</li></ul>","description":"tính từ: sợ sệt vì mê tín","pronounce":"'iəri"}]