[{"id":63159,"word":"ETB (End of Transmission Block)","html":"<h1>ETB (End of Transmission Block)</h1><h3><i>//</i></h3><ul><li>(Tech) khối chấm dứt truyền đạt</li></ul>","description":"(Tech) khối chấm dứt truyền đạt","pronounce":""},{"id":63167,"word":"ETX (End of Text)","html":"<h1>ETX (End of Text)</h1><h3><i>//</i></h3><ul><li>(Tech) chấm dứt văn bản</li></ul>","description":"(Tech) chấm dứt văn bản","pronounce":""},{"id":63166,"word":"Ethernet","html":"<h1>Ethernet</h1><h3><i>//</i></h3><ul><li>(Tech) mạng Ethernet (itơnet)</li></ul>","description":"(Tech) mạng Ethernet (itơnet)","pronounce":""},{"id":63165,"word":"Ethernet cable","html":"<h1>Ethernet cable</h1><h3><i>//</i></h3><ul><li>(Tech) cáp Ethernet</li></ul>","description":"(Tech) cáp Ethernet","pronounce":""},{"id":77879,"word":"et al","html":"<h1>et al</h1><h3><i>//</i></h3><ul><li>đặc ngữ La tinh</li><li>những người hoặc thứ khác</li></ul>","description":"đặc ngữ La tinh","pronounce":""},{"id":15881,"word":"et cetera","html":"<h1>et cetera</h1><h3><i>/it'setrə/</i></h3><h2>danh từ</h2><ul><li>vân vân ((viết tắt) etc)</li></ul>","description":"danh từ: vân vân ((viết tắt) etc)","pronounce":"it'setrə"},{"id":15882,"word":"et ceteras","html":"<h1>et ceteras</h1><h3><i>/it'setrəz/</i></h3><h2>danh từ số nhiều</h2><ul><li>những cái phụ thêm; đồ linh tinh</li></ul>","description":"danh từ số nhiều: những cái phụ thêm; đồ linh tinh","pronounce":"it'setrəz"},{"id":77880,"word":"et seq","html":"<h1>et seq</h1><h3><i>//</i></h3><ul><li>đặc ngữ La tinh</li><li>và tiếp theo</li></ul>","description":"đặc ngữ La tinh","pronounce":""},{"id":15883,"word":"eta","html":"<h1>eta</h1><h3><i>/'i:tə/</i></h3><h2>danh từ</h2><ul><li>Eta (chữ cái Hy-lạp)</li></ul>","description":"danh từ: Eta (chữ cái Hy-lạp)","pronounce":"'i:tə"},{"id":105256,"word":"eta","html":"<h1>eta</h1><h3><i>//</i></h3><ul><li>eta (&#951;)</li></ul>","description":"eta (&#951;)","pronounce":""},{"id":15884,"word":"etacism","html":"<h1>etacism</h1><h3><i>/'eitəsiʤm/</i></h3><h2>danh từ</h2><ul><li>lối phát âm của chữ eta theo kiểu Anh)</li></ul>","description":"danh từ: lối phát âm của chữ eta theo kiểu Anh)","pronounce":"'eitəsiʤm"},{"id":77881,"word":"etalon","html":"<h1>etalon</h1><h3><i>//</i></h3>* danh từ<br/><ul><li>chuẩn; mẫu (đo lường)</li></ul>","description":"chuẩn; mẫu (đo lường)","pronounce":""},{"id":77882,"word":"etamine","html":"<h1>etamine</h1><h3><i>//</i></h3>* danh từ<br/><ul><li>vải mỏng; vải mặt rây</li></ul>","description":"vải mỏng; vải mặt rây","pronounce":""},{"id":77883,"word":"etape","html":"<h1>etape</h1><h3><i>//</i></h3>* danh từ<br/><ul><li>trạm nghỉ (quân đội)</li><li>lộ trình trong một ngày</li></ul>","description":"trạm nghỉ (quân đội)","pronounce":""},{"id":77884,"word":"etc","html":"<h1>etc</h1><h3><i>//</i></h3><ul><li>nhiều hơn nữa, vân vân (khi liệt kê)</li></ul>","description":"nhiều hơn nữa, vân vân (khi liệt kê)","pronounce":""},{"id":15885,"word":"etcetera","html":"<h1>etcetera</h1><h3><i>/it'setrə/</i></h3><h2>danh từ</h2><ul><li>vân vân ((viết tắt) etc)</li></ul>","description":"danh từ: vân vân ((viết tắt) etc)","pronounce":"it'setrə"},{"id":77885,"word":"etceteras","html":"<h1>etceteras</h1><h3><i>//</i></h3>* danh từ số nhiều<br/><ul><li>những thứ kèm theo; đồ linh tinh<ul style=\"list-style-type:circle\"><li> It's not just food for the guests - there are all the eceteras as well:<i>Đâu phải chỉ có thức ăn cho khách thôi - mà còn bao nhiêu thứ linh tinh khác nữa</i></li></ul></li></ul>","description":"những thứ kèm theo; đồ linh tinh","pronounce":""},{"id":15886,"word":"etch","html":"<h1>etch</h1><h3><i>/etʃ/</i></h3><h2>động từ</h2><ul><li>khắc axit</li></ul>","description":"động từ: khắc axit","pronounce":"etʃ"},{"id":63162,"word":"etch","html":"<h1>etch</h1><h3><i>//</i></h3><ul><li>(Tech) khắc (đ)</li></ul>","description":"(Tech) khắc (đ)","pronounce":""},{"id":63160,"word":"etch pattern","html":"<h1>etch pattern</h1><h3><i>//</i></h3><ul><li>(Tech) dạng hình mạch khắc</li></ul>","description":"(Tech) dạng hình mạch khắc","pronounce":""},{"id":63161,"word":"etch pit density","html":"<h1>etch pit density</h1><h3><i>//</i></h3><ul><li>(Tech) mật độ khắc lõm, mật độ thực khắc</li></ul>","description":"(Tech) mật độ khắc lõm, mật độ thực khắc","pronounce":""},{"id":77886,"word":"etchant","html":"<h1>etchant</h1><h3><i>//</i></h3>* danh từ<br/><ul><li>chất khắc ăn mòn</li></ul>","description":"chất khắc ăn mòn","pronounce":""},{"id":63163,"word":"etched circuit","html":"<h1>etched circuit</h1><h3><i>//</i></h3><ul><li>(Tech) mạch khắc</li></ul>","description":"(Tech) mạch khắc","pronounce":""},{"id":15887,"word":"etcher","html":"<h1>etcher</h1><h3><i>/'etʃə/</i></h3><h2>danh từ</h2><ul><li>thợ khắc axit</li></ul>","description":"danh từ: thợ khắc axit","pronounce":"'etʃə"},{"id":15888,"word":"etching","html":"<h1>etching</h1><h3><i>/'etʃiɳ/</i></h3><h2>danh từ</h2><ul><li>sự khắc axit; thuật khắc axit</li><li>bản khắc axit</li></ul>","description":"danh từ: sự khắc axit; thuật khắc axit","pronounce":"'etʃiɳ"},{"id":63164,"word":"etching method","html":"<h1>etching method</h1><h3><i>//</i></h3><ul><li>(Tech) phương pháp khắc</li></ul>","description":"(Tech) phương pháp khắc","pronounce":""},{"id":77887,"word":"etching-knife","html":"<h1>etching-knife</h1><h3><i>//</i></h3>* danh từ<br/><ul><li>dao khắc axit</li></ul>","description":"dao khắc axit","pronounce":""},{"id":15889,"word":"etching-needle","html":"<h1>etching-needle</h1><h3><i>/'etʃiɳ,ni:dl/</i></h3><h2>danh từ</h2><ul><li>mùi khắc axit</li></ul>","description":"danh từ: mùi khắc axit","pronounce":"'etʃiɳ,ni:dl"},{"id":77888,"word":"etd","html":"<h1>etd</h1><h3><i>//</i></h3>* (viết tắt)<br/><ul><li>giờ khởi hành ước chừng (Estimated time of departure)</li></ul>","description":"giờ khởi hành ước chừng (Estimated time of departure)","pronounce":""},{"id":15890,"word":"eternal","html":"<h1>eternal</h1><h3><i>/i:'tə:nl/</i></h3><h2>tính từ</h2><ul><li>tồn tại, đời đời, vĩnh viễn, bất diệt</li><li>(thông tục) không ngừng, thường xuyên<ul style=\"list-style-type:circle\"><li>eternal disputes:<i> những sự cãi cọ không ngừng</i></li></ul></li></ul><h2>thành ngữ</h2><ol><li>the Eternal<ul><li>thượng đế</li></ul></li><li>the eternal triangle<ul><li>(xem) triangle</li></ul></li></ol>","description":"tính từ: tồn tại, đời đời, vĩnh viễn, bất diệt","pronounce":"i:'tə:nl"},{"id":15891,"word":"eternalise","html":"<h1>eternalise</h1><h3><i>/i:'tə:naiz/</i></h3><h2>ngoại động từ</h2><ul><li>làm cho vĩnh viễn, làm cho bất diệt<ul style=\"list-style-type:circle\"><li>to eternize someone's memory:<i> làm cho ai đời đời tưởng nhớ đến</i></li></ul></li></ul>","description":"ngoại động từ: làm cho vĩnh viễn, làm cho bất diệt","pronounce":"i:'tə:naiz"},{"id":15892,"word":"eternality","html":"<h1>eternality</h1><h3><i>/,i:tə:'næiti/</i></h3><h2>tính từ</h2><ul><li>tính vĩnh viễn, tính bất diệt</li></ul>","description":"tính từ: tính vĩnh viễn, tính bất diệt","pronounce":",i:tə:'næiti"},{"id":15893,"word":"eternalize","html":"<h1>eternalize</h1><h3><i>/i:'tə:naiz/</i></h3><h2>ngoại động từ</h2><ul><li>làm cho vĩnh viễn, làm cho bất diệt<ul style=\"list-style-type:circle\"><li>to eternize someone's memory:<i> làm cho ai đời đời tưởng nhớ đến</i></li></ul></li></ul>","description":"ngoại động từ: làm cho vĩnh viễn, làm cho bất diệt","pronounce":"i:'tə:naiz"},{"id":15894,"word":"eternally","html":"<h1>eternally</h1><h3><i>/i:'tə:nəli/</i></h3><h2>phó từ</h2><ul><li>đời đời, vĩnh viễn, bất diệt</li><li>không ngừng, thường xuyên</li></ul>","description":"phó từ: đời đời, vĩnh viễn, bất diệt","pronounce":"i:'tə:nəli"},{"id":15895,"word":"eternise","html":"<h1>eternise</h1><h3><i>/i:'tə:naiz/</i></h3><h2>ngoại động từ</h2><ul><li>làm cho vĩnh viễn, làm cho bất diệt<ul style=\"list-style-type:circle\"><li>to eternize someone's memory:<i> làm cho ai đời đời tưởng nhớ đến</i></li></ul></li></ul>","description":"ngoại động từ: làm cho vĩnh viễn, làm cho bất diệt","pronounce":"i:'tə:naiz"},{"id":15896,"word":"eternity","html":"<h1>eternity</h1><h3><i>/i:'tə:niti/</i></h3><h2>danh từ</h2><ul><li>tính vĩnh viễn, tính bất diệt</li><li>ngàn xưa, thời gian vô tận (trong tương lai)</li><li>tiếng tăm muôn đời</li><li>đời sau</li><li>(số nhiều) những sự thật bất di bất dịch</li></ul>","description":"danh từ: tính vĩnh viễn, tính bất diệt","pronounce":"i:'tə:niti"},{"id":77889,"word":"eternization","html":"<h1>eternization</h1><h3><i>//</i></h3><ul><li>xem eternize</li></ul>","description":"xem eternize","pronounce":""},{"id":15897,"word":"eternize","html":"<h1>eternize</h1><h3><i>/i:'tə:naiz/</i></h3><h2>ngoại động từ</h2><ul><li>làm cho vĩnh viễn, làm cho bất diệt<ul style=\"list-style-type:circle\"><li>to eternize someone's memory:<i> làm cho ai đời đời tưởng nhớ đến</i></li></ul></li></ul>","description":"ngoại động từ: làm cho vĩnh viễn, làm cho bất diệt","pronounce":"i:'tə:naiz"},{"id":77890,"word":"etesian","html":"<h1>etesian</h1><h3><i>//</i></h3>* tính từ<br/><ul><li>xuất hiện hàng năm đúng kì hạn<ul style=\"list-style-type:circle\"><li> etesian winds:<i>gió bấc mùa hè ở Địa Trung Hải</i></li></ul></li></ul>","description":"xuất hiện hàng năm đúng kì hạn","pronounce":""},{"id":15898,"word":"ethane","html":"<h1>ethane</h1><h3><i>/'eθein/</i></h3><h2>danh từ</h2><ul><li>(hoá học) Etan</li></ul>","description":"danh từ: (hoá học) Etan","pronounce":"'eθein"},{"id":77891,"word":"ethanol","html":"<h1>ethanol</h1><h3><i>//</i></h3>* danh từ<br/><ul><li>(hoá học) ethanol</li></ul>","description":"(hoá học) ethanol","pronounce":""},{"id":77892,"word":"ethanolamine","html":"<h1>ethanolamine</h1><h3><i>//</i></h3>* danh từ<br/><ul><li>(hoá học) etanolamin</li></ul>","description":"(hoá học) etanolamin","pronounce":""},{"id":77893,"word":"ethene","html":"<h1>ethene</h1><h3><i>//</i></h3>* danh từ<br/><ul><li>(hoá học) eten; etilen</li></ul>","description":"(hoá học) eten; etilen","pronounce":""},{"id":15899,"word":"ether","html":"<h1>ether</h1><h3><i>/'i:θə/</i></h3><h2>danh từ</h2><ul><li>bầu trời trong sáng; chín tầng mây, thinh không</li><li>(vật lý) Ête<ul style=\"list-style-type:circle\"><li>luminiferous ether:<i> ête ánh sáng</i></li></ul></li><li>hoá Ête</li></ul>","description":"danh từ: bầu trời trong sáng; chín tầng mây, thinh không","pronounce":"'i:θə"},{"id":15900,"word":"ethereal","html":"<h1>ethereal</h1><h3><i>/i:'θiəriəl/</i></h3><h2>tính từ</h2><ul><li>cao tít tầng mây, trên thinh không</li><li>nhẹ lâng lâng; thanh tao</li><li>thiên tiên, siêu trần</li><li>(vật lý) (thuộc) Ête; giống Ête</li><li>(hoá học) (thuộc) Ête; giống Ête</li></ul><h2>thành ngữ</h2><ol><li>ethereal oil<ul><li>tinh dầu</li></ul></li></ol>","description":"tính từ: cao tít tầng mây, trên thinh không","pronounce":"i:'θiəriəl"},{"id":15901,"word":"ethereality","html":"<h1>ethereality</h1><h3><i>/i:,θiəri'æliti/</i></h3><h2>danh từ</h2><ul><li>tính nhẹ lâng lâng</li><li>tính thiên tiên, tính siêu trần</li></ul>","description":"danh từ: tính nhẹ lâng lâng","pronounce":"i:,θiəri'æliti"},{"id":15902,"word":"etherealization","html":"<h1>etherealization</h1><h3><i>/i:,θiəriəlai'zeiʃ/</i></h3><h2>danh từ</h2><ul><li>sự làm nhẹ lâng lâng</li><li>sự làm cho giống thiên tiên, sự siêu trần hoá</li></ul>","description":"danh từ: sự làm nhẹ lâng lâng","pronounce":"i:,θiəriəlai'zeiʃ"},{"id":15903,"word":"etherealize","html":"<h1>etherealize</h1><h3><i>/i:'θiəriəlaiz/</i></h3><h2>ngoại động từ</h2><ul><li>làm nhẹ lâng lâng</li><li>làm cho giống thiên tiên, siêu trần hoá</li></ul>","description":"ngoại động từ: làm nhẹ lâng lâng","pronounce":"i:'θiəriəlaiz"},{"id":15904,"word":"ethereally","html":"<h1>ethereally</h1><h3><i>/i:'θiəriəli/</i></h3><h2>phó từ</h2><ul><li>nhẹ lâng lâng</li><li>như thiên tiên, siêu trần</li></ul>","description":"phó từ: nhẹ lâng lâng","pronounce":"i:'θiəriəli"},{"id":15905,"word":"etherial","html":"<h1>etherial</h1><h3><i>/i:'θiəriəl/</i></h3><h2>tính từ</h2><ul><li>cao tít tầng mây, trên thinh không</li><li>nhẹ lâng lâng; thanh tao</li><li>thiên tiên, siêu trần</li><li>(vật lý) (thuộc) Ête; giống Ête</li><li>(hoá học) (thuộc) Ête; giống Ête</li></ul><h2>thành ngữ</h2><ol><li>ethereal oil<ul><li>tinh dầu</li></ul></li></ol>","description":"tính từ: cao tít tầng mây, trên thinh không","pronounce":"i:'θiəriəl"},{"id":77894,"word":"etheric","html":"<h1>etheric</h1><h3><i>//</i></h3><ul><li>xem ether</li></ul>","description":"xem ether","pronounce":""},{"id":15906,"word":"etherification","html":"<h1>etherification</h1><h3><i>/i:,θerifi'keiʃn/</i></h3><h2>danh từ</h2><ul><li>(hoá học) sự hoá Ête</li></ul>","description":"danh từ: (hoá học) sự hoá Ête","pronounce":"i:,θerifi'keiʃn"},{"id":15907,"word":"etherify","html":"<h1>etherify</h1><h3><i>/i:'θerifai/</i></h3><h2>ngoại động từ</h2><ul><li>(hoá học) hoá Ête</li></ul>","description":"ngoại động từ: (hoá học) hoá Ête","pronounce":"i:'θerifai"},{"id":15908,"word":"etherise","html":"<h1>etherise</h1><h3><i>/'i:θəraiz/</i></h3><h2>ngoại động từ</h2><ul><li>(hoá học) hoá ête</li><li>(y học) cho ngửi ête, gây mê ête</li></ul>","description":"ngoại động từ: (hoá học) hoá ête","pronounce":"'i:θəraiz"},{"id":15909,"word":"etherism","html":"<h1>etherism</h1><h3><i>/'i:θərizm/</i></h3><h2>danh từ</h2><ul><li>(y học) trạng thái nhiễm ête</li></ul>","description":"danh từ: (y học) trạng thái nhiễm ête","pronounce":"'i:θərizm"},{"id":15910,"word":"etherization","html":"<h1>etherization</h1><h3><i>/,i:θərai'zeiʃn/</i></h3><h2>danh từ</h2><ul><li>(y học) sự gây mê ête</li></ul>","description":"danh từ: (y học) sự gây mê ête","pronounce":",i:θərai'zeiʃn"},{"id":15911,"word":"etherize","html":"<h1>etherize</h1><h3><i>/'i:θəraiz/</i></h3><h2>ngoại động từ</h2><ul><li>(hoá học) hoá ête</li><li>(y học) cho ngửi ête, gây mê ête</li></ul>","description":"ngoại động từ: (hoá học) hoá ête","pronounce":"'i:θəraiz"},{"id":77895,"word":"etherizer","html":"<h1>etherizer</h1><h3><i>//</i></h3><ul><li>xem etherize</li></ul>","description":"xem etherize","pronounce":""},{"id":77896,"word":"ethernet","html":"<h1>ethernet</h1><h3><i>//</i></h3><ul><li>Phần cứng, định ước, tiêu chuẩn ghép nối của một loại mạng cục bộ, do hãng Xerox Corporation đưa ra đầu tiên, có khả năng liên kết đến 1024 nút trong một mạng bus</li></ul>","description":"Phần cứng, định ước, tiêu chuẩn ghép nối của một loại mạng cục bộ, do hãng Xerox Corporation đưa ra đầu tiên, có khả năng liên kết đến 1024 nút trong một mạng bus","pronounce":""},{"id":77897,"word":"ethertalk","html":"<h1>ethertalk</h1><h3><i>//</i></h3><ul><li>Một bộ phận bổ sung trong phần cứng của mạng cục bộ Ethernet, do các hãng Apple và 3 Com hợp tác chế độ, được thiết kế để hoạt động cùng với hệ điều hành mạng AppleShare EtherTalk truyền dữ liệu qua cáp đồng trục với tốc độ 10 megabit mỗi giây (tốc độ của Ethernet), trong khi tốc độ của mạng AppleTalk chỉ có 230 kilobit/giây</li></ul>","description":"Một bộ phận bổ sung trong phần cứng của mạng cục bộ Ethernet, do các hãng Apple và 3 Com hợp tác chế độ, được thiết kế để hoạt động cùng với hệ điều hành mạng AppleShare EtherTalk truyền dữ liệu qua cáp đồng trục với tốc độ 10 megabit mỗi giây (tốc độ của Ethernet), trong khi tốc độ của mạng AppleTalk chỉ có 230 kilobit/giây","pronounce":""},{"id":15912,"word":"ethic","html":"<h1>ethic</h1><h3><i>/'eθik/</i></h3><h2>tính từ</h2><ul><li>(thuộc) đạo đức, (thuộc) luân thường đạo lý</li><li>(từ Mỹ,nghĩa Mỹ) hợp với luân thường đạo lý, đúng với nguyên tắc xử thế (một cá nhân); đúng nội quy (một tổ chức)</li><li>đúng quy cách (thuốc)</li><li>chỉ bán theo đơn thầy thuốc</li></ul>","description":"tính từ: (thuộc) đạo đức, (thuộc) luân thường đạo lý","pronounce":"'eθik"},{"id":15913,"word":"ethical","html":"<h1>ethical</h1><h3><i>/'eθik/</i></h3><h2>tính từ</h2><ul><li>(thuộc) đạo đức, (thuộc) luân thường đạo lý</li><li>(từ Mỹ,nghĩa Mỹ) hợp với luân thường đạo lý, đúng với nguyên tắc xử thế (một cá nhân); đúng nội quy (một tổ chức)</li><li>đúng quy cách (thuốc)</li><li>chỉ bán theo đơn thầy thuốc</li></ul>","description":"tính từ: (thuộc) đạo đức, (thuộc) luân thường đạo lý","pronounce":"'eθik"},{"id":77898,"word":"ethicality","html":"<h1>ethicality</h1><h3><i>//</i></h3><ul><li>xem ethical</li></ul>","description":"xem ethical","pronounce":""},{"id":15914,"word":"ethically","html":"<h1>ethically</h1><h3><i>/'eθikəli/</i></h3><h2>phó từ</h2><ul><li>có đạo đức, theo đúng luân thường đạo lý, hợp với luân thường đạo lý</li></ul>","description":"phó từ: có đạo đức, theo đúng luân thường đạo lý, hợp với luân thường đạo lý","pronounce":"'eθikəli"},{"id":77899,"word":"ethicalness","html":"<h1>ethicalness</h1><h3><i>//</i></h3><ul><li>xem ethical</li></ul>","description":"xem ethical","pronounce":""},{"id":15915,"word":"ethicize","html":"<h1>ethicize</h1><h3><i>/'eθisaiz/</i></h3><h2>ngoại động từ</h2><ul><li>làm cho hợp với đạo đức, làm cho hợp với luân thường đạo lý</li></ul>","description":"ngoại động từ: làm cho hợp với đạo đức, làm cho hợp với luân thường đạo lý","pronounce":"'eθisaiz"},{"id":15916,"word":"ethics","html":"<h1>ethics</h1><h3><i>/'eθiks/</i></h3><h2>danh từ,  số nhiều dùng như số ít</h2><ul><li>đạo đức, luân thường đạo lý</li><li>đạo đức học</li><li>(từ Mỹ,nghĩa Mỹ) nguyên tắc xử thế (một cá nhân); nội quy (một tổ chức)</li></ul>","description":"danh từ,  số nhiều dùng như số ít: đạo đức, luân thường đạo lý","pronounce":"'eθiks"},{"id":77900,"word":"ethionine","html":"<h1>ethionine</h1><h3><i>//</i></h3>* danh từ<br/><ul><li>(hoá học) ethionin</li></ul>","description":"(hoá học) ethionin","pronounce":""},{"id":15917,"word":"ethiopian","html":"<h1>ethiopian</h1><h3><i>/,i:θi'oupjən/</i></h3><h2>tính từ</h2><ul><li>(thuộc) Ê-ti-ô-pi</li></ul><h2>danh từ</h2><ul><li>người Ê-ti-ô-pi</li></ul>","description":"tính từ: (thuộc) Ê-ti-ô-pi","pronounce":",i:θi'oupjən"},{"id":15918,"word":"ethiopianism","html":"<h1>ethiopianism</h1><h3><i>/,i:θi'oupjənizm/</i></h3><h2>danh từ</h2><ul><li>phong trào \" Châu phi của người Châu phi\"</li></ul>","description":"danh từ: phong trào \" Châu phi của người Châu phi\"","pronounce":",i:θi'oupjənizm"},{"id":15919,"word":"ethmoid","html":"<h1>ethmoid</h1><h3><i>/'eθmɔid/</i></h3><h2>tính từ</h2><ul><li>(giải phẫu) (thuộc) xương sàng<ul style=\"list-style-type:circle\"><li>ethmoid bone:<i> xương sàng</i></li></ul></li></ul>","description":"tính từ: (giải phẫu) (thuộc) xương sàng","pronounce":"'eθmɔid"},{"id":77901,"word":"ethmoiditis","html":"<h1>ethmoiditis</h1><h3><i>//</i></h3>* danh từ<br/><ul><li>(y học) viêm xương sàng</li></ul>","description":"(y học) viêm xương sàng","pronounce":""},{"id":15920,"word":"ethnarch","html":"<h1>ethnarch</h1><h3><i>/'etnɑ:k/</i></h3><h2>danh từ</h2><ul><li>thống đốc; tỉnh trưởng</li></ul>","description":"danh từ: thống đốc; tỉnh trưởng","pronounce":"'etnɑ:k"},{"id":77902,"word":"ethnarchy","html":"<h1>ethnarchy</h1><h3><i>//</i></h3><ul><li>xem ethnarch</li></ul>","description":"xem ethnarch","pronounce":""},{"id":15921,"word":"ethnic","html":"<h1>ethnic</h1><h3><i>/'eθnik/</i></h3><h2>tính từ</h2><ul><li>thuộc dân tộc, thuộc tộc người</li><li>không theo tôn giáo nào, vô thần</li></ul>","description":"tính từ: thuộc dân tộc, thuộc tộc người","pronounce":"'eθnik"},{"id":15922,"word":"ethnical","html":"<h1>ethnical</h1><h3><i>/'eθnik/</i></h3><h2>tính từ</h2><ul><li>thuộc dân tộc, thuộc tộc người</li><li>không theo tôn giáo nào, vô thần</li></ul>","description":"tính từ: thuộc dân tộc, thuộc tộc người","pronounce":"'eθnik"},{"id":15923,"word":"ethnicalism","html":"<h1>ethnicalism</h1><h3><i>/'eθnikəlizm/</i></h3><h2>danh từ</h2><ul><li>sự không theo tôn giáo nào, chủ nghĩa vô thần</li></ul>","description":"danh từ: sự không theo tôn giáo nào, chủ nghĩa vô thần","pronounce":"'eθnikəlizm"},{"id":15924,"word":"ethnically","html":"<h1>ethnically</h1><h3><i>/'eθnikəli/</i></h3><h2>phó từ</h2><ul><li>về mặt dân tộc</li></ul>","description":"phó từ: về mặt dân tộc","pronounce":"'eθnikəli"},{"id":77903,"word":"ethnicism","html":"<h1>ethnicism</h1><h3><i>//</i></h3>* danh từ<br/><ul><li>xem ethnicalism</li></ul>","description":"xem ethnicalism","pronounce":""},{"id":77904,"word":"ethnicity","html":"<h1>ethnicity</h1><h3><i>//</i></h3>* danh từ<br/><ul><li>tính cách sắc tộc</li></ul>","description":"tính cách sắc tộc","pronounce":""},{"id":77905,"word":"ethnobotany","html":"<h1>ethnobotany</h1><h3><i>//</i></h3>* danh từ<br/><ul><li>thực vật dân tộc học</li></ul>","description":"thực vật dân tộc học","pronounce":""},{"id":15925,"word":"ethnocentric","html":"<h1>ethnocentric</h1><h3><i>/,eθnou'sentrik/</i></h3><h2>tính từ</h2><ul><li>vị chủng, cho dân tộc mình là hơn cả</li></ul>","description":"tính từ: vị chủng, cho dân tộc mình là hơn cả","pronounce":",eθnou'sentrik"},{"id":77906,"word":"ethnocentrically","html":"<h1>ethnocentrically</h1><h3><i>//</i></h3><ul><li>xem ethnocentrism</li></ul>","description":"xem ethnocentrism","pronounce":""},{"id":77907,"word":"ethnocentricity","html":"<h1>ethnocentricity</h1><h3><i>//</i></h3><ul><li>xem ethnocentrism</li></ul>","description":"xem ethnocentrism","pronounce":""},{"id":15926,"word":"ethnocentrism","html":"<h1>ethnocentrism</h1><h3><i>/,eθnou'sentrizm/</i></h3><h2>danh từ</h2><ul><li>chủ nghĩa vị chủng, thuyết cho dân tộc mình là hơn cả</li></ul>","description":"danh từ: chủ nghĩa vị chủng, thuyết cho dân tộc mình là hơn cả","pronounce":",eθnou'sentrizm"},{"id":77908,"word":"ethnogenic","html":"<h1>ethnogenic</h1><h3><i>//</i></h3>* tính từ<br/><ul><li>(thuộc) khoa nguồn gốc tộc người</li></ul>","description":"(thuộc) khoa nguồn gốc tộc người","pronounce":""},{"id":77909,"word":"ethnogeny","html":"<h1>ethnogeny</h1><h3><i>//</i></h3>* danh từ<br/><ul><li>khoa nguồn gốc tộc người</li></ul>","description":"khoa nguồn gốc tộc người","pronounce":""},{"id":15927,"word":"ethnographer","html":"<h1>ethnographer</h1><h3><i>/eθ'nɔgrəfə/</i></h3><h2>danh từ</h2><ul><li>nhà dân tộc học</li></ul>","description":"danh từ: nhà dân tộc học","pronounce":"eθ'nɔgrəfə"},{"id":15928,"word":"ethnographic","html":"<h1>ethnographic</h1><h3><i>/,eθnou'græfik/</i></h3><h2>tính từ</h2><ul><li>(thuộc) dân tộc học</li></ul>","description":"tính từ: (thuộc) dân tộc học","pronounce":",eθnou'græfik"},{"id":15929,"word":"ethnographical","html":"<h1>ethnographical</h1><h3><i>/,eθnou'græfik/</i></h3><h2>tính từ</h2><ul><li>(thuộc) dân tộc học</li></ul>","description":"tính từ: (thuộc) dân tộc học","pronounce":",eθnou'græfik"},{"id":77910,"word":"ethnographically","html":"<h1>ethnographically</h1><h3><i>//</i></h3><ul><li>xem ethnography</li></ul>","description":"xem ethnography","pronounce":""},{"id":15930,"word":"ethnography","html":"<h1>ethnography</h1><h3><i>/eθ'nɔgrəfi/</i></h3><h2>danh từ</h2><ul><li>khoa mô tả dân tộc</li><li>dân tộc học</li></ul>","description":"danh từ: khoa mô tả dân tộc","pronounce":"eθ'nɔgrəfi"},{"id":15931,"word":"ethnologic","html":"<h1>ethnologic</h1><h3><i>/,eθnou'lɔdʤik/</i></h3><h2>tính từ</h2><ul><li>(thuộc) dân tộc học</li></ul>","description":"tính từ: (thuộc) dân tộc học","pronounce":",eθnou'lɔdʤik"},{"id":15932,"word":"ethnological","html":"<h1>ethnological</h1><h3><i>/,eθnou'lɔdʤik/</i></h3><h2>tính từ</h2><ul><li>(thuộc) dân tộc học</li></ul>","description":"tính từ: (thuộc) dân tộc học","pronounce":",eθnou'lɔdʤik"},{"id":77911,"word":"ethnologically","html":"<h1>ethnologically</h1><h3><i>//</i></h3><ul><li>xem ethnology</li></ul>","description":"xem ethnology","pronounce":""},{"id":15933,"word":"ethnologist","html":"<h1>ethnologist</h1><h3><i>/eθ'nɔlədʤist/</i></h3><h2>danh từ</h2><ul><li>nhà dân tộc học</li></ul>","description":"danh từ: nhà dân tộc học","pronounce":"eθ'nɔlədʤist"},{"id":15934,"word":"ethnology","html":"<h1>ethnology</h1><h3><i>/eθ'nɔlədʤi/</i></h3><h2>danh từ</h2><ul><li>dân tộc học</li></ul>","description":"danh từ: dân tộc học","pronounce":"eθ'nɔlədʤi"},{"id":77912,"word":"ethnomusicological","html":"<h1>ethnomusicological</h1><h3><i>//</i></h3>* tính từ<br/><ul><li>thuộc âm nhạc dân tộc</li></ul>","description":"thuộc âm nhạc dân tộc","pronounce":""},{"id":77913,"word":"ethnomusicologist","html":"<h1>ethnomusicologist</h1><h3><i>//</i></h3>* danh từ<br/><ul><li>nhà nghiên cứu âm nhạc dân tộc</li></ul>","description":"nhà nghiên cứu âm nhạc dân tộc","pronounce":""},{"id":77914,"word":"ethnomusicology","html":"<h1>ethnomusicology</h1><h3><i>//</i></h3>* danh từ<br/><ul><li>khoa âm nhạc dân tộc</li></ul>","description":"khoa âm nhạc dân tộc","pronounce":""},{"id":77915,"word":"ethnopsychology","html":"<h1>ethnopsychology</h1><h3><i>//</i></h3>* danh từ<br/><ul><li>khoa tâm lý học dân tộc</li></ul>","description":"khoa tâm lý học dân tộc","pronounce":""},{"id":77916,"word":"ethnos","html":"<h1>ethnos</h1><h3><i>//</i></h3>* danh từ<br/><ul><li>đoàn thể huyết tộc</li></ul>","description":"đoàn thể huyết tộc","pronounce":""},{"id":77917,"word":"ethography","html":"<h1>ethography</h1><h3><i>//</i></h3>* danh từ<br/><ul><li>phong tục học</li></ul>","description":"phong tục học","pronounce":""},{"id":15935,"word":"ethological","html":"<h1>ethological</h1><h3><i>/,i:θou'lɔdʤikəl/</i></h3><h2>tính từ</h2><ul><li>(thuộc) phong tục học</li></ul>","description":"tính từ: (thuộc) phong tục học","pronounce":",i:θou'lɔdʤikəl"},{"id":77918,"word":"ethologist","html":"<h1>ethologist</h1><h3><i>//</i></h3><ul><li>xem ethology</li></ul>","description":"xem ethology","pronounce":""},{"id":15936,"word":"ethology","html":"<h1>ethology</h1><h3><i>/i:'θɔlədʤi/</i></h3><h2>danh từ</h2><ul><li>phong tục học</li></ul>","description":"danh từ: phong tục học","pronounce":"i:'θɔlədʤi"},{"id":15937,"word":"ethos","html":"<h1>ethos</h1><h3><i>/'i:θɔs/</i></h3><h2>danh từ</h2><ul><li>đặc tính, nét đặc biệt (của một tập thể, một chủng tộc...)</li></ul>","description":"danh từ: đặc tính, nét đặc biệt (của một tập thể, một chủng tộc...)","pronounce":"'i:θɔs"},{"id":77919,"word":"ethoxy","html":"<h1>ethoxy</h1><h3><i>//</i></h3>* tính từ<br/><ul><li>thuộc etoxila</li></ul>","description":"thuộc etoxila","pronounce":""},{"id":77920,"word":"ethoxyl","html":"<h1>ethoxyl</h1><h3><i>//</i></h3>* danh từ<br/><ul><li>(hoá học) etoxila</li></ul>","description":"(hoá học) etoxila","pronounce":""},{"id":15938,"word":"ethyl","html":"<h1>ethyl</h1><h3><i>/'eθil/</i></h3><h2>danh từ</h2><ul><li>(hoá học) Etyla</li></ul>","description":"danh từ: (hoá học) Etyla","pronounce":"'eθil"},{"id":15939,"word":"ethylamine","html":"<h1>ethylamine</h1><h3><i>/'eθiləmin/</i></h3><h2>danh từ</h2><ul><li>(hoá học) Etylamin</li></ul>","description":"danh từ: (hoá học) Etylamin","pronounce":"'eθiləmin"},{"id":77921,"word":"ethylation","html":"<h1>ethylation</h1><h3><i>//</i></h3>* danh từ<br/><ul><li>sự úa vàng (cây); tình trạng xanh xao (người)</li></ul>","description":"sự úa vàng (cây); tình trạng xanh xao (người)","pronounce":""},{"id":15940,"word":"ethylene","html":"<h1>ethylene</h1><h3><i>/'eθili:n/</i></h3><h2>danh từ</h2><ul><li>(hoá học) Etylen</li></ul>","description":"danh từ: (hoá học) Etylen","pronounce":"'eθili:n"},{"id":77922,"word":"ethylenic","html":"<h1>ethylenic</h1><h3><i>//</i></h3><ul><li>xem ethylene</li></ul>","description":"xem ethylene","pronounce":""},{"id":15941,"word":"ethylic","html":"<h1>ethylic</h1><h3><i>/'eθilik/</i></h3><h2>tính từ</h2><ul><li>hoá Etylic</li></ul>","description":"tính từ: hoá Etylic","pronounce":"'eθilik"},{"id":77923,"word":"ethylize","html":"<h1>ethylize</h1><h3><i>//</i></h3>* ngoại động từ<br/><ul><li>etyl hoá</li></ul>","description":"etyl hoá","pronounce":""},{"id":15942,"word":"etiolate","html":"<h1>etiolate</h1><h3><i>/'i:tiouleit/</i></h3><h2>ngoại động từ</h2><ul><li>làm úa vàng (cây cối); làm nhợt nhạt, làm xanh xao (người)</li></ul>","description":"ngoại động từ: làm úa vàng (cây cối); làm nhợt nhạt, làm xanh xao (người)","pronounce":"'i:tiouleit"},{"id":15943,"word":"etiolation","html":"<h1>etiolation</h1><h3><i>/,i:tiou'leiʃn/</i></h3><h2>danh từ</h2><ul><li>sự làm úa vàng (cây); sự làm nhợt nhạt, làm xanh xao (người)</li></ul>","description":"danh từ: sự làm úa vàng (cây); sự làm nhợt nhạt, làm xanh xao (người)","pronounce":",i:tiou'leiʃn"},{"id":77924,"word":"etiologic","html":"<h1>etiologic</h1><h3><i>//</i></h3><ul><li>xem etiology</li></ul>","description":"xem etiology","pronounce":""},{"id":77925,"word":"etiologically","html":"<h1>etiologically</h1><h3><i>//</i></h3><ul><li>xem etiology</li></ul>","description":"xem etiology","pronounce":""},{"id":77926,"word":"etiologist","html":"<h1>etiologist</h1><h3><i>//</i></h3><ul><li>xem etiology</li></ul>","description":"xem etiology","pronounce":""},{"id":15944,"word":"etiology","html":"<h1>etiology</h1><h3><i>/,i:ti'ɔlədʤi/</i></h3><h2>danh từ</h2><ul><li>thuyết nguyên nhân</li><li>(y học) khoa nguyên nhân bệnh</li></ul>","description":"danh từ: thuyết nguyên nhân","pronounce":",i:ti'ɔlədʤi"},{"id":15945,"word":"etiquette","html":"<h1>etiquette</h1><h3><i>/,eti'ket/</i></h3><h2>danh từ</h2><ul><li>phép xã giao</li><li>nghi lễ, nghi thức</li><li>quy ước mặc nhận (của một giới chuyên môn)<ul style=\"list-style-type:circle\"><li>medical etiquette:<i> quy ước mặc nhận trong giới y</i></li></ul></li></ul>","description":"danh từ: phép xã giao","pronounce":",eti'ket"},{"id":15946,"word":"etna","html":"<h1>etna</h1><h3><i>/'etnə/</i></h3><h2>danh từ\t\t\t\t\t\t\t\t  /</h2><ul><li>đèn cồn</li></ul>","description":"danh từ\t\t\t\t\t\t\t\t  /: đèn cồn","pronounce":"'etnə"},{"id":15947,"word":"eton collar","html":"<h1>eton collar</h1><h3><i>/'i:tn'kɔlə/</i></h3><h2>danh từ</h2><ul><li>cổ cồn cứng (mang ngoài cổ áo)</li></ul>","description":"danh từ: cổ cồn cứng (mang ngoài cổ áo)","pronounce":"'i:tn'kɔlə"},{"id":15948,"word":"eton crop","html":"<h1>eton crop</h1><h3><i>/'i:tn'krɔp/</i></h3><h2>danh từ</h2><ul><li>lối cắt tóc con trai (đàn bà)</li></ul>","description":"danh từ: lối cắt tóc con trai (đàn bà)","pronounce":"'i:tn'krɔp"},{"id":15949,"word":"eton jacket","html":"<h1>eton jacket</h1><h3><i>/'i:tn'dʤækit/</i></h3><h2>danh từ</h2><ul><li>áo ngoài ngắn cũn cỡn (của trẻ em học trường I-tơn, một trường của trẻ em quý tộc ở Anh)</li></ul>","description":"danh từ: áo ngoài ngắn cũn cỡn (của trẻ em học trường I-tơn, một trường của trẻ em quý tộc ở Anh)","pronounce":"'i:tn'dʤækit"},{"id":77927,"word":"ettings","html":"<h1>ettings</h1><h3><i>//</i></h3>* danh từ số nhiều<br/><ul><li>vật thu được</li></ul>","description":"vật thu được","pronounce":""},{"id":77928,"word":"ettle","html":"<h1>ettle</h1><h3><i>//</i></h3>* ngoại động từ<br/><ul><li>thu được</li></ul>","description":"thu được","pronounce":""},{"id":77929,"word":"etude","html":"<h1>etude</h1><h3><i>//</i></h3>* danh từ<br/><ul><li>(âm nhạc) khúc luyện</li></ul>","description":"(âm nhạc) khúc luyện","pronounce":""},{"id":15950,"word":"etui","html":"<h1>etui</h1><h3><i>/e'twi:/</i></h3><h2>danh từ</h2><ul><li>túi nhỏ (đựng kim, tăm xỉa răng...)</li></ul>","description":"danh từ: túi nhỏ (đựng kim, tăm xỉa răng...)","pronounce":"e'twi:"},{"id":15951,"word":"etwee","html":"<h1>etwee</h1><h3><i>/e'twi:/</i></h3><h2>danh từ</h2><ul><li>túi nhỏ (đựng kim, tăm xỉa răng...)</li></ul>","description":"danh từ: túi nhỏ (đựng kim, tăm xỉa răng...)","pronounce":"e'twi:"},{"id":77930,"word":"etx","html":"<h1>etx</h1><h3><i>/ack handshaking/</i></h3><ul><li>thiết lập quan hệ, tay bắt tay (một phương pháp để kiểm soát sự thông suốt của quá trình truyền tin nối tiếp giữa hai thiết bị, sao cho thiết bị này chỉ phát tin khi thiết bị kia đã sẵn sàng nhận)</li></ul>","description":"thiết lập quan hệ, tay bắt tay (một phương pháp để kiểm soát sự thông suốt của quá trình truyền tin nối tiếp giữa hai thiết bị, sao cho thiết bị này chỉ phát tin khi thiết bị kia đã sẵn sàng nhận)","pronounce":"ack handshaking"},{"id":15952,"word":"etymologer","html":"<h1>etymologer</h1><h3><i>/,eti'mɔlədʤə/</i></h3><h2>danh từ</h2><ul><li>nhà từ nguyên học</li></ul>","description":"danh từ: nhà từ nguyên học","pronounce":",eti'mɔlədʤə"},{"id":15953,"word":"etymologic","html":"<h1>etymologic</h1><h3><i>/,etimə'lɔdʤik/</i></h3><h2>tính từ</h2><ul><li>(thuộc) từ nguyên; theo từ nguyên</li></ul>","description":"tính từ: (thuộc) từ nguyên; theo từ nguyên","pronounce":",etimə'lɔdʤik"},{"id":15954,"word":"etymological","html":"<h1>etymological</h1><h3><i>/,etimə'lɔdʤik/</i></h3><h2>tính từ</h2><ul><li>(thuộc) từ nguyên; theo từ nguyên</li></ul>","description":"tính từ: (thuộc) từ nguyên; theo từ nguyên","pronounce":",etimə'lɔdʤik"},{"id":77931,"word":"etymologically","html":"<h1>etymologically</h1><h3><i>//</i></h3><ul><li>xem etymological</li></ul>","description":"xem etymological","pronounce":""},{"id":15955,"word":"etymologise","html":"<h1>etymologise</h1><h3><i>/,eti'mɔlədʤaiz/</i></h3><h2>ngoại động từ</h2><ul><li>tìm nguồn gốc của (một từ); cho nguồn gốc của (một từ); đưa ra nguồn gốc của (một từ)</li></ul><h2>nội động từ</h2><ul><li>nghiên cứu về từ nguyên</li></ul>","description":"ngoại động từ: tìm nguồn gốc của (một từ); cho nguồn gốc của (một từ); đưa ra nguồn gốc của (một từ)","pronounce":",eti'mɔlədʤaiz"},{"id":77932,"word":"etymologist","html":"<h1>etymologist</h1><h3><i>//</i></h3>* danh từ<br/><ul><li>nhà từ nguyên học</li></ul>","description":"nhà từ nguyên học","pronounce":""},{"id":15956,"word":"etymologize","html":"<h1>etymologize</h1><h3><i>/,eti'mɔlədʤaiz/</i></h3><h2>ngoại động từ</h2><ul><li>tìm nguồn gốc của (một từ); cho nguồn gốc của (một từ); đưa ra nguồn gốc của (một từ)</li></ul><h2>nội động từ</h2><ul><li>nghiên cứu về từ nguyên</li></ul>","description":"ngoại động từ: tìm nguồn gốc của (một từ); cho nguồn gốc của (một từ); đưa ra nguồn gốc của (một từ)","pronounce":",eti'mɔlədʤaiz"},{"id":15957,"word":"etymology","html":"<h1>etymology</h1><h3><i>/,eti'mɔlədʤi/</i></h3><h2>danh từ</h2><ul><li>từ nguyên</li><li>từ nguyên học</li></ul>","description":"danh từ: từ nguyên","pronounce":",eti'mɔlədʤi"},{"id":15958,"word":"etymon","html":"<h1>etymon</h1><h3><i>/'etimɔn/</i></h3><h2>danh từ</h2><ul><li>(ngôn ngữ học) căn tổ từ nguyên</li></ul>","description":"danh từ: (ngôn ngữ học) căn tổ từ nguyên","pronounce":"'etimɔn"}]